[{"id":833,"s":15,"a":1,"p":1,"t":"الٓر ۚ","c1":"ﭑﭒ","c2":"ﱁﱂ","l":3,"ct":"word"},{"id":835,"s":15,"a":1,"p":2,"t":"تِلْكَ","c1":"ﭓ","c2":"ﱃ","l":3,"ct":"word"},{"id":836,"s":15,"a":1,"p":3,"t":"ءَايَـٰتُ","c1":"ﭔ","c2":"ﱄ","l":3,"ct":"word"},{"id":837,"s":15,"a":1,"p":4,"t":"ٱلْكِتَـٰبِ","c1":"ﭕ","c2":"ﱅ","l":3,"ct":"word"},{"id":838,"s":15,"a":1,"p":5,"t":"وَقُرْءَانٍۢ","c1":"ﭖ","c2":"ﱆ","l":3,"ct":"word"},{"id":839,"s":15,"a":1,"p":6,"t":"مُّبِينٍۢ","c1":"ﭗ","c2":"ﱇ","l":3,"ct":"word"},{"id":840,"s":15,"a":1,"p":7,"t":"١","c1":"ﭘ","c2":"ﱈ","l":3,"ct":"end"},{"id":1944,"s":15,"a":2,"p":1,"t":"رُّبَمَا","c1":"ﭙ","c2":"ﱉ","l":3,"ct":"word"},{"id":1945,"s":15,"a":2,"p":2,"t":"يَوَدُّ","c1":"ﭚ","c2":"ﱊ","l":3,"ct":"word"},{"id":1946,"s":15,"a":2,"p":3,"t":"ٱلَّذِينَ","c1":"ﭛ","c2":"ﱋ","l":4,"ct":"word"},{"id":1947,"s":15,"a":2,"p":4,"t":"كَفَرُوا۟","c1":"ﭜ","c2":"ﱌ","l":4,"ct":"word"},{"id":1948,"s":15,"a":2,"p":5,"t":"لَوْ","c1":"ﭝ","c2":"ﱍ","l":4,"ct":"word"},{"id":1949,"s":15,"a":2,"p":6,"t":"كَانُوا۟","c1":"ﭞ","c2":"ﱎ","l":4,"ct":"word"},{"id":1950,"s":15,"a":2,"p":7,"t":"مُسْلِمِينَ","c1":"ﭟ","c2":"ﱏ","l":4,"ct":"word"},{"id":1951,"s":15,"a":2,"p":8,"t":"٢","c1":"ﭠ","c2":"ﱐ","l":4,"ct":"end"},{"id":3132,"s":15,"a":3,"p":1,"t":"ذَرْهُمْ","c1":"ﭡ","c2":"ﱑ","l":4,"ct":"word"},{"id":3133,"s":15,"a":3,"p":2,"t":"يَأْكُلُوا۟","c1":"ﭢ","c2":"ﱒ","l":4,"ct":"word"},{"id":3134,"s":15,"a":3,"p":3,"t":"وَيَتَمَتَّعُوا۟","c1":"ﭣ","c2":"ﱓ","l":5,"ct":"word"},{"id":3135,"s":15,"a":3,"p":4,"t":"وَيُلْهِهِمُ","c1":"ﭤ","c2":"ﱔ","l":5,"ct":"word"},{"id":3136,"s":15,"a":3,"p":5,"t":"ٱلْأَمَلُ ۖ","c1":"ﭥﭦ","c2":"ﱕﱖ","l":5,"ct":"word"},{"id":3138,"s":15,"a":3,"p":6,"t":"فَسَوْفَ","c1":"ﭧ","c2":"ﱗ","l":5,"ct":"word"},{"id":3139,"s":15,"a":3,"p":7,"t":"يَعْلَمُونَ","c1":"ﭨ","c2":"ﱘ","l":5,"ct":"word"},{"id":3140,"s":15,"a":3,"p":8,"t":"٣","c1":"ﭩ","c2":"ﱙ","l":5,"ct":"end"},{"id":3605,"s":15,"a":4,"p":1,"t":"وَمَآ","c1":"ﭪ","c2":"ﱚ","l":5,"ct":"word"},{"id":3606,"s":15,"a":4,"p":2,"t":"أَهْلَكْنَا","c1":"ﭫ","c2":"ﱛ","l":5,"ct":"word"},{"id":3607,"s":15,"a":4,"p":3,"t":"مِن","c1":"ﭬ","c2":"ﱜ","l":6,"ct":"word"},{"id":3608,"s":15,"a":4,"p":4,"t":"قَرْيَةٍ","c1":"ﭭ","c2":"ﱝ","l":6,"ct":"word"},{"id":3609,"s":15,"a":4,"p":5,"t":"إِلَّا","c1":"ﭮ","c2":"ﱞ","l":6,"ct":"word"},{"id":3610,"s":15,"a":4,"p":6,"t":"وَلَهَا","c1":"ﭯ","c2":"ﱟ","l":6,"ct":"word"},{"id":3611,"s":15,"a":4,"p":7,"t":"كِتَابٌۭ","c1":"ﭰ","c2":"ﱠ","l":6,"ct":"word"},{"id":3612,"s":15,"a":4,"p":8,"t":"مَّعْلُومٌۭ","c1":"ﭱ","c2":"ﱡ","l":6,"ct":"word"},{"id":3613,"s":15,"a":4,"p":9,"t":"٤","c1":"ﭲ","c2":"ﱢ","l":6,"ct":"end"},{"id":5180,"s":15,"a":5,"p":1,"t":"مَّا","c1":"ﭳ","c2":"ﱣ","l":6,"ct":"word"},{"id":5181,"s":15,"a":5,"p":2,"t":"تَسْبِقُ","c1":"ﭴ","c2":"ﱤ","l":6,"ct":"word"},{"id":5182,"s":15,"a":5,"p":3,"t":"مِنْ","c1":"ﭵ","c2":"ﱥ","l":6,"ct":"word"},{"id":5183,"s":15,"a":5,"p":4,"t":"أُمَّةٍ","c1":"ﭶ","c2":"ﱦ","l":6,"ct":"word"},{"id":5184,"s":15,"a":5,"p":5,"t":"أَجَلَهَا","c1":"ﭷ","c2":"ﱧ","l":7,"ct":"word"},{"id":5185,"s":15,"a":5,"p":6,"t":"وَمَا","c1":"ﭸ","c2":"ﱨ","l":7,"ct":"word"},{"id":5186,"s":15,"a":5,"p":7,"t":"يَسْتَـْٔخِرُونَ","c1":"ﭹ","c2":"ﱩ","l":7,"ct":"word"},{"id":5187,"s":15,"a":5,"p":8,"t":"٥","c1":"ﭺ","c2":"ﱪ","l":7,"ct":"end"},{"id":6937,"s":15,"a":6,"p":1,"t":"وَقَالُوا۟","c1":"ﭻ","c2":"ﱫ","l":7,"ct":"word"},{"id":6938,"s":15,"a":6,"p":2,"t":"يَـٰٓأَيُّهَا","c1":"ﭼ","c2":"ﱬ","l":7,"ct":"word"},{"id":6939,"s":15,"a":6,"p":3,"t":"ٱلَّذِى","c1":"ﭽ","c2":"ﱭ","l":7,"ct":"word"},{"id":6940,"s":15,"a":6,"p":4,"t":"نُزِّلَ","c1":"ﭾ","c2":"ﱮ","l":7,"ct":"word"},{"id":6941,"s":15,"a":6,"p":5,"t":"عَلَيْهِ","c1":"ﭿ","c2":"ﱯ","l":7,"ct":"word"},{"id":6942,"s":15,"a":6,"p":6,"t":"ٱلذِّكْرُ","c1":"ﮀ","c2":"ﱰ","l":8,"ct":"word"},{"id":6943,"s":15,"a":6,"p":7,"t":"إِنَّكَ","c1":"ﮁ","c2":"ﱱ","l":8,"ct":"word"},{"id":6944,"s":15,"a":6,"p":8,"t":"لَمَجْنُونٌۭ","c1":"ﮂ","c2":"ﱲ","l":8,"ct":"word"},{"id":6945,"s":15,"a":6,"p":9,"t":"٦","c1":"ﮃ","c2":"ﱳ","l":8,"ct":"end"},{"id":8233,"s":15,"a":7,"p":1,"t":"لَّوْ","c1":"ﮄ","c2":"ﱴ","l":8,"ct":"word"},{"id":8234,"s":15,"a":7,"p":2,"t":"مَا","c1":"ﮅ","c2":"ﱵ","l":8,"ct":"word"},{"id":8235,"s":15,"a":7,"p":3,"t":"تَأْتِينَا","c1":"ﮆ","c2":"ﱶ","l":8,"ct":"word"},{"id":8236,"s":15,"a":7,"p":4,"t":"بِٱلْمَلَـٰٓئِكَةِ","c1":"ﮇ","c2":"ﱷ","l":8,"ct":"word"},{"id":8237,"s":15,"a":7,"p":5,"t":"إِن","c1":"ﮈ","c2":"ﱸ","l":8,"ct":"word"},{"id":8238,"s":15,"a":7,"p":6,"t":"كُنتَ","c1":"ﮉ","c2":"ﱹ","l":8,"ct":"word"},{"id":8239,"s":15,"a":7,"p":7,"t":"مِنَ","c1":"ﮊ","c2":"ﱺ","l":9,"ct":"word"},{"id":8240,"s":15,"a":7,"p":8,"t":"ٱلصَّـٰدِقِينَ","c1":"ﮋ","c2":"ﱻ","l":9,"ct":"word"},{"id":8241,"s":15,"a":7,"p":9,"t":"٧","c1":"ﮌ","c2":"ﱼ","l":9,"ct":"end"},{"id":9493,"s":15,"a":8,"p":1,"t":"مَا","c1":"ﮍ","c2":"ﱽ","l":9,"ct":"word"},{"id":9494,"s":15,"a":8,"p":2,"t":"نُنَزِّلُ","c1":"ﮎ","c2":"ﱾ","l":9,"ct":"word"},{"id":9495,"s":15,"a":8,"p":3,"t":"ٱلْمَلَـٰٓئِكَةَ","c1":"ﮏ","c2":"ﱿ","l":9,"ct":"word"},{"id":9496,"s":15,"a":8,"p":4,"t":"إِلَّا","c1":"ﮐ","c2":"ﲀ","l":9,"ct":"word"},{"id":9497,"s":15,"a":8,"p":5,"t":"بِٱلْحَقِّ","c1":"ﮑ","c2":"ﲁ","l":9,"ct":"word"},{"id":9498,"s":15,"a":8,"p":6,"t":"وَمَا","c1":"ﮒ","c2":"ﲂ","l":9,"ct":"word"},{"id":9499,"s":15,"a":8,"p":7,"t":"كَانُوٓا۟","c1":"ﮓ","c2":"ﲃ","l":9,"ct":"word"},{"id":9500,"s":15,"a":8,"p":8,"t":"إِذًۭا","c1":"ﮔ","c2":"ﲄ","l":10,"ct":"word"},{"id":9501,"s":15,"a":8,"p":9,"t":"مُّنظَرِينَ","c1":"ﮕ","c2":"ﲅ","l":10,"ct":"word"},{"id":9502,"s":15,"a":8,"p":10,"t":"٨","c1":"ﮖ","c2":"ﲆ","l":10,"ct":"end"},{"id":10575,"s":15,"a":9,"p":1,"t":"إِنَّا","c1":"ﮗ","c2":"ﲇ","l":10,"ct":"word"},{"id":10576,"s":15,"a":9,"p":2,"t":"نَحْنُ","c1":"ﮘ","c2":"ﲈ","l":10,"ct":"word"},{"id":10577,"s":15,"a":9,"p":3,"t":"نَزَّلْنَا","c1":"ﮙ","c2":"ﲉ","l":10,"ct":"word"},{"id":10578,"s":15,"a":9,"p":4,"t":"ٱلذِّكْرَ","c1":"ﮚ","c2":"ﲊ","l":10,"ct":"word"},{"id":10579,"s":15,"a":9,"p":5,"t":"وَإِنَّا","c1":"ﮛ","c2":"ﲋ","l":10,"ct":"word"},{"id":10580,"s":15,"a":9,"p":6,"t":"لَهُۥ","c1":"ﮜ","c2":"ﲌ","l":10,"ct":"word"},{"id":10581,"s":15,"a":9,"p":7,"t":"لَحَـٰفِظُونَ","c1":"ﮝ","c2":"ﲍ","l":10,"ct":"word"},{"id":10582,"s":15,"a":9,"p":8,"t":"٩","c1":"ﮞ","c2":"ﲎ","l":10,"ct":"end"},{"id":11721,"s":15,"a":10,"p":1,"t":"وَلَقَدْ","c1":"ﮟ","c2":"ﲏ","l":11,"ct":"word"},{"id":11722,"s":15,"a":10,"p":2,"t":"أَرْسَلْنَا","c1":"ﮠ","c2":"ﲐ","l":11,"ct":"word"},{"id":11723,"s":15,"a":10,"p":3,"t":"مِن","c1":"ﮡ","c2":"ﲑ","l":11,"ct":"word"},{"id":11724,"s":15,"a":10,"p":4,"t":"قَبْلِكَ","c1":"ﮢ","c2":"ﲒ","l":11,"ct":"word"},{"id":11725,"s":15,"a":10,"p":5,"t":"فِى","c1":"ﮣ","c2":"ﲓ","l":11,"ct":"word"},{"id":11726,"s":15,"a":10,"p":6,"t":"شِيَعِ","c1":"ﮤ","c2":"ﲔ","l":11,"ct":"word"},{"id":11727,"s":15,"a":10,"p":7,"t":"ٱلْأَوَّلِينَ","c1":"ﮥ","c2":"ﲕ","l":11,"ct":"word"},{"id":11728,"s":15,"a":10,"p":8,"t":"١٠","c1":"ﮦ","c2":"ﲖ","l":11,"ct":"end"},{"id":13206,"s":15,"a":11,"p":1,"t":"وَمَا","c1":"ﮧ","c2":"ﲗ","l":11,"ct":"word"},{"id":13207,"s":15,"a":11,"p":2,"t":"يَأْتِيهِم","c1":"ﮨ","c2":"ﲘ","l":11,"ct":"word"},{"id":13208,"s":15,"a":11,"p":3,"t":"مِّن","c1":"ﮩ","c2":"ﲙ","l":12,"ct":"word"},{"id":13209,"s":15,"a":11,"p":4,"t":"رَّسُولٍ","c1":"ﮪ","c2":"ﲚ","l":12,"ct":"word"},{"id":13210,"s":15,"a":11,"p":5,"t":"إِلَّا","c1":"ﮫ","c2":"ﲛ","l":12,"ct":"word"},{"id":13211,"s":15,"a":11,"p":6,"t":"كَانُوا۟","c1":"ﮬ","c2":"ﲜ","l":12,"ct":"word"},{"id":13212,"s":15,"a":11,"p":7,"t":"بِهِۦ","c1":"ﮭ","c2":"ﲝ","l":12,"ct":"word"},{"id":13213,"s":15,"a":11,"p":8,"t":"يَسْتَهْزِءُونَ","c1":"ﮮ","c2":"ﲞ","l":12,"ct":"word"},{"id":13214,"s":15,"a":11,"p":9,"t":"١١","c1":"ﮯ","c2":"ﲟ","l":12,"ct":"end"},{"id":13537,"s":15,"a":12,"p":1,"t":"كَذَٰلِكَ","c1":"ﮰ","c2":"ﲠ","l":12,"ct":"word"},{"id":13538,"s":15,"a":12,"p":2,"t":"نَسْلُكُهُۥ","c1":"ﮱ","c2":"ﲡ","l":12,"ct":"word"},{"id":13539,"s":15,"a":12,"p":3,"t":"فِى","c1":"ﯓ","c2":"ﲢ","l":13,"ct":"word"},{"id":13540,"s":15,"a":12,"p":4,"t":"قُلُوبِ","c1":"ﯔ","c2":"ﲣ","l":13,"ct":"word"},{"id":13541,"s":15,"a":12,"p":5,"t":"ٱلْمُجْرِمِينَ","c1":"ﯕ","c2":"ﲤ","l":13,"ct":"word"},{"id":13542,"s":15,"a":12,"p":6,"t":"١٢","c1":"ﯖ","c2":"ﲥ","l":13,"ct":"end"},{"id":14925,"s":15,"a":13,"p":1,"t":"لَا","c1":"ﯗ","c2":"ﲦ","l":13,"ct":"word"},{"id":14926,"s":15,"a":13,"p":2,"t":"يُؤْمِنُونَ","c1":"ﯘ","c2":"ﲧ","l":13,"ct":"word"},{"id":14927,"s":15,"a":13,"p":3,"t":"بِهِۦ ۖ","c1":"ﯙﯚ","c2":"ﲨ","l":13,"ct":"word"},{"id":14929,"s":15,"a":13,"p":4,"t":"وَقَدْ","c1":"ﯛ","c2":"ﲩ","l":13,"ct":"word"},{"id":14930,"s":15,"a":13,"p":5,"t":"خَلَتْ","c1":"ﯜ","c2":"ﲪ","l":13,"ct":"word"},{"id":14931,"s":15,"a":13,"p":6,"t":"سُنَّةُ","c1":"ﯝ","c2":"ﲫ","l":13,"ct":"word"},{"id":14932,"s":15,"a":13,"p":7,"t":"ٱلْأَوَّلِينَ","c1":"ﯞ","c2":"ﲬ","l":13,"ct":"word"},{"id":14933,"s":15,"a":13,"p":8,"t":"١٣","c1":"ﯟ","c2":"ﲭ","l":14,"ct":"end"},{"id":16703,"s":15,"a":14,"p":1,"t":"وَلَوْ","c1":"ﯠ","c2":"ﲮ","l":14,"ct":"word"},{"id":16704,"s":15,"a":14,"p":2,"t":"فَتَحْنَا","c1":"ﯡ","c2":"ﲯ","l":14,"ct":"word"},{"id":16705,"s":15,"a":14,"p":3,"t":"عَلَيْهِم","c1":"ﯢ","c2":"ﲰ","l":14,"ct":"word"},{"id":16706,"s":15,"a":14,"p":4,"t":"بَابًۭا","c1":"ﯣ","c2":"ﲱ","l":14,"ct":"word"},{"id":16707,"s":15,"a":14,"p":5,"t":"مِّنَ","c1":"ﯤ","c2":"ﲲ","l":14,"ct":"word"},{"id":16708,"s":15,"a":14,"p":6,"t":"ٱلسَّمَآءِ","c1":"ﯥ","c2":"ﲳ","l":14,"ct":"word"},{"id":16709,"s":15,"a":14,"p":7,"t":"فَظَلُّوا۟","c1":"ﯦ","c2":"ﲴ","l":14,"ct":"word"},{"id":16710,"s":15,"a":14,"p":8,"t":"فِيهِ","c1":"ﯧ","c2":"ﲵ","l":14,"ct":"word"},{"id":16711,"s":15,"a":14,"p":9,"t":"يَعْرُجُونَ","c1":"ﯨ","c2":"ﲶ","l":14,"ct":"word"},{"id":16712,"s":15,"a":14,"p":10,"t":"١٤","c1":"ﯩ","c2":"ﲷ","l":14,"ct":"end"},{"id":17885,"s":15,"a":15,"p":1,"t":"لَقَالُوٓا۟","c1":"ﯪ","c2":"ﲸ","l":15,"ct":"word"},{"id":17886,"s":15,"a":15,"p":2,"t":"إِنَّمَا","c1":"ﯫ","c2":"ﲹ","l":15,"ct":"word"},{"id":17887,"s":15,"a":15,"p":3,"t":"سُكِّرَتْ","c1":"ﯬ","c2":"ﲺ","l":15,"ct":"word"},{"id":17888,"s":15,"a":15,"p":4,"t":"أَبْصَـٰرُنَا","c1":"ﯭ","c2":"ﲻ","l":15,"ct":"word"},{"id":17889,"s":15,"a":15,"p":5,"t":"بَلْ","c1":"ﯮ","c2":"ﲼ","l":15,"ct":"word"},{"id":17890,"s":15,"a":15,"p":6,"t":"نَحْنُ","c1":"ﯯ","c2":"ﲽ","l":15,"ct":"word"},{"id":17891,"s":15,"a":15,"p":7,"t":"قَوْمٌۭ","c1":"ﯰ","c2":"ﲾ","l":15,"ct":"word"},{"id":17892,"s":15,"a":15,"p":8,"t":"مَّسْحُورُونَ","c1":"ﯱ","c2":"ﲿ","l":15,"ct":"word"},{"id":17893,"s":15,"a":15,"p":9,"t":"١٥","c1":"ﯲ","c2":"ﳀ","l":15,"ct":"end"}]