[{"id":71923,"s":2,"a":102,"p":1,"t":"وَٱتَّبَعُوا۟","c1":"ﭑ","c2":"ﱁ","l":1,"ct":"word"},{"id":71924,"s":2,"a":102,"p":2,"t":"مَا","c1":"ﭒ","c2":"ﱂ","l":1,"ct":"word"},{"id":71925,"s":2,"a":102,"p":3,"t":"تَتْلُوا۟","c1":"ﭓ","c2":"ﱃ","l":1,"ct":"word"},{"id":71926,"s":2,"a":102,"p":4,"t":"ٱلشَّيَـٰطِينُ","c1":"ﭔ","c2":"ﱄ","l":1,"ct":"word"},{"id":71927,"s":2,"a":102,"p":5,"t":"عَلَىٰ","c1":"ﭕ","c2":"ﱅ","l":1,"ct":"word"},{"id":71928,"s":2,"a":102,"p":6,"t":"مُلْكِ","c1":"ﭖ","c2":"ﱆ","l":1,"ct":"word"},{"id":71929,"s":2,"a":102,"p":7,"t":"سُلَيْمَـٰنَ ۖ","c1":"ﭗﭘ","c2":"ﱇﱈ","l":1,"ct":"word"},{"id":71931,"s":2,"a":102,"p":8,"t":"وَمَا","c1":"ﭙ","c2":"ﱉ","l":1,"ct":"word"},{"id":71932,"s":2,"a":102,"p":9,"t":"كَفَرَ","c1":"ﭚ","c2":"ﱊ","l":1,"ct":"word"},{"id":71933,"s":2,"a":102,"p":10,"t":"سُلَيْمَـٰنُ","c1":"ﭛ","c2":"ﱋ","l":2,"ct":"word"},{"id":71934,"s":2,"a":102,"p":11,"t":"وَلَـٰكِنَّ","c1":"ﭜ","c2":"ﱌ","l":2,"ct":"word"},{"id":71935,"s":2,"a":102,"p":12,"t":"ٱلشَّيَـٰطِينَ","c1":"ﭝ","c2":"ﱍ","l":2,"ct":"word"},{"id":71936,"s":2,"a":102,"p":13,"t":"كَفَرُوا۟","c1":"ﭞ","c2":"ﱎ","l":2,"ct":"word"},{"id":71937,"s":2,"a":102,"p":14,"t":"يُعَلِّمُونَ","c1":"ﭟ","c2":"ﱏ","l":2,"ct":"word"},{"id":71938,"s":2,"a":102,"p":15,"t":"ٱلنَّاسَ","c1":"ﭠ","c2":"ﱐ","l":2,"ct":"word"},{"id":71939,"s":2,"a":102,"p":16,"t":"ٱلسِّحْرَ","c1":"ﭡ","c2":"ﱑ","l":3,"ct":"word"},{"id":71940,"s":2,"a":102,"p":17,"t":"وَمَآ","c1":"ﭢ","c2":"ﱒ","l":3,"ct":"word"},{"id":71941,"s":2,"a":102,"p":18,"t":"أُنزِلَ","c1":"ﭣ","c2":"ﱓ","l":3,"ct":"word"},{"id":71942,"s":2,"a":102,"p":19,"t":"عَلَى","c1":"ﭤ","c2":"ﱔ","l":3,"ct":"word"},{"id":71943,"s":2,"a":102,"p":20,"t":"ٱلْمَلَكَيْنِ","c1":"ﭥ","c2":"ﱕ","l":3,"ct":"word"},{"id":71944,"s":2,"a":102,"p":21,"t":"بِبَابِلَ","c1":"ﭦ","c2":"ﱖ","l":3,"ct":"word"},{"id":71945,"s":2,"a":102,"p":22,"t":"هَـٰرُوتَ","c1":"ﭧ","c2":"ﱗ","l":3,"ct":"word"},{"id":71946,"s":2,"a":102,"p":23,"t":"وَمَـٰرُوتَ ۚ","c1":"ﭨﭩ","c2":"ﱘﱙ","l":3,"ct":"word"},{"id":71948,"s":2,"a":102,"p":24,"t":"وَمَا","c1":"ﭪ","c2":"ﱚ","l":4,"ct":"word"},{"id":71949,"s":2,"a":102,"p":25,"t":"يُعَلِّمَانِ","c1":"ﭫ","c2":"ﱛ","l":4,"ct":"word"},{"id":71950,"s":2,"a":102,"p":26,"t":"مِنْ","c1":"ﭬ","c2":"ﱜ","l":4,"ct":"word"},{"id":71951,"s":2,"a":102,"p":27,"t":"أَحَدٍ","c1":"ﭭ","c2":"ﱝ","l":4,"ct":"word"},{"id":71952,"s":2,"a":102,"p":28,"t":"حَتَّىٰ","c1":"ﭮ","c2":"ﱞ","l":4,"ct":"word"},{"id":71953,"s":2,"a":102,"p":29,"t":"يَقُولَآ","c1":"ﭯ","c2":"ﱟ","l":4,"ct":"word"},{"id":71954,"s":2,"a":102,"p":30,"t":"إِنَّمَا","c1":"ﭰ","c2":"ﱠ","l":4,"ct":"word"},{"id":71955,"s":2,"a":102,"p":31,"t":"نَحْنُ","c1":"ﭱ","c2":"ﱡ","l":4,"ct":"word"},{"id":71956,"s":2,"a":102,"p":32,"t":"فِتْنَةٌۭ","c1":"ﭲ","c2":"ﱢ","l":4,"ct":"word"},{"id":71957,"s":2,"a":102,"p":33,"t":"فَلَا","c1":"ﭳ","c2":"ﱣ","l":4,"ct":"word"},{"id":71958,"s":2,"a":102,"p":34,"t":"تَكْفُرْ ۖ","c1":"ﭴﭵ","c2":"ﱤﱥ","l":5,"ct":"word"},{"id":71960,"s":2,"a":102,"p":35,"t":"فَيَتَعَلَّمُونَ","c1":"ﭶ","c2":"ﱦ","l":5,"ct":"word"},{"id":71961,"s":2,"a":102,"p":36,"t":"مِنْهُمَا","c1":"ﭷ","c2":"ﱧ","l":5,"ct":"word"},{"id":71962,"s":2,"a":102,"p":37,"t":"مَا","c1":"ﭸ","c2":"ﱨ","l":5,"ct":"word"},{"id":71963,"s":2,"a":102,"p":38,"t":"يُفَرِّقُونَ","c1":"ﭹ","c2":"ﱩ","l":5,"ct":"word"},{"id":71964,"s":2,"a":102,"p":39,"t":"بِهِۦ","c1":"ﭺ","c2":"ﱪ","l":5,"ct":"word"},{"id":71965,"s":2,"a":102,"p":40,"t":"بَيْنَ","c1":"ﭻ","c2":"ﱫ","l":5,"ct":"word"},{"id":71966,"s":2,"a":102,"p":41,"t":"ٱلْمَرْءِ","c1":"ﭼ","c2":"ﱬ","l":5,"ct":"word"},{"id":71967,"s":2,"a":102,"p":42,"t":"وَزَوْجِهِۦ ۚ","c1":"ﭽﭾ","c2":"ﱭﱮ","l":6,"ct":"word"},{"id":71969,"s":2,"a":102,"p":43,"t":"وَمَا","c1":"ﭿ","c2":"ﱯ","l":6,"ct":"word"},{"id":71970,"s":2,"a":102,"p":44,"t":"هُم","c1":"ﮀ","c2":"ﱰ","l":6,"ct":"word"},{"id":71971,"s":2,"a":102,"p":45,"t":"بِضَآرِّينَ","c1":"ﮁ","c2":"ﱱ","l":6,"ct":"word"},{"id":71972,"s":2,"a":102,"p":46,"t":"بِهِۦ","c1":"ﮂ","c2":"ﱲ","l":6,"ct":"word"},{"id":71973,"s":2,"a":102,"p":47,"t":"مِنْ","c1":"ﮃ","c2":"ﱳ","l":6,"ct":"word"},{"id":71974,"s":2,"a":102,"p":48,"t":"أَحَدٍ","c1":"ﮄ","c2":"ﱴ","l":6,"ct":"word"},{"id":71975,"s":2,"a":102,"p":49,"t":"إِلَّا","c1":"ﮅ","c2":"ﱵ","l":6,"ct":"word"},{"id":71976,"s":2,"a":102,"p":50,"t":"بِإِذْنِ","c1":"ﮆ","c2":"ﱶ","l":6,"ct":"word"},{"id":71977,"s":2,"a":102,"p":51,"t":"ٱللَّهِ ۚ","c1":"ﮇﮈ","c2":"ﱷﱸ","l":6,"ct":"word"},{"id":71979,"s":2,"a":102,"p":52,"t":"وَيَتَعَلَّمُونَ","c1":"ﮉ","c2":"ﱹ","l":7,"ct":"word"},{"id":71980,"s":2,"a":102,"p":53,"t":"مَا","c1":"ﮊ","c2":"ﱺ","l":7,"ct":"word"},{"id":71981,"s":2,"a":102,"p":54,"t":"يَضُرُّهُمْ","c1":"ﮋ","c2":"ﱻ","l":7,"ct":"word"},{"id":71982,"s":2,"a":102,"p":55,"t":"وَلَا","c1":"ﮌ","c2":"ﱼ","l":7,"ct":"word"},{"id":71983,"s":2,"a":102,"p":56,"t":"يَنفَعُهُمْ ۚ","c1":"ﮍﮎ","c2":"ﱽﱾ","l":7,"ct":"word"},{"id":71985,"s":2,"a":102,"p":57,"t":"وَلَقَدْ","c1":"ﮏ","c2":"ﱿ","l":7,"ct":"word"},{"id":71986,"s":2,"a":102,"p":58,"t":"عَلِمُوا۟","c1":"ﮐ","c2":"ﲀ","l":7,"ct":"word"},{"id":71987,"s":2,"a":102,"p":59,"t":"لَمَنِ","c1":"ﮑ","c2":"ﲁ","l":7,"ct":"word"},{"id":71988,"s":2,"a":102,"p":60,"t":"ٱشْتَرَىٰهُ","c1":"ﮒ","c2":"ﲂ","l":8,"ct":"word"},{"id":71989,"s":2,"a":102,"p":61,"t":"مَا","c1":"ﮓ","c2":"ﲃ","l":8,"ct":"word"},{"id":71990,"s":2,"a":102,"p":62,"t":"لَهُۥ","c1":"ﮔ","c2":"ﲄ","l":8,"ct":"word"},{"id":71991,"s":2,"a":102,"p":63,"t":"فِى","c1":"ﮕ","c2":"ﲅ","l":8,"ct":"word"},{"id":71992,"s":2,"a":102,"p":64,"t":"ٱلْـَٔاخِرَةِ","c1":"ﮖ","c2":"ﲆ","l":8,"ct":"word"},{"id":71993,"s":2,"a":102,"p":65,"t":"مِنْ","c1":"ﮗ","c2":"ﲇ","l":8,"ct":"word"},{"id":71994,"s":2,"a":102,"p":66,"t":"خَلَـٰقٍۢ ۚ","c1":"ﮘﮙ","c2":"ﲈﲉ","l":8,"ct":"word"},{"id":71996,"s":2,"a":102,"p":67,"t":"وَلَبِئْسَ","c1":"ﮚ","c2":"ﲊ","l":8,"ct":"word"},{"id":71997,"s":2,"a":102,"p":68,"t":"مَا","c1":"ﮛ","c2":"ﲋ","l":8,"ct":"word"},{"id":71998,"s":2,"a":102,"p":69,"t":"شَرَوْا۟","c1":"ﮜ","c2":"ﲌ","l":8,"ct":"word"},{"id":71999,"s":2,"a":102,"p":70,"t":"بِهِۦٓ","c1":"ﮝ","c2":"ﲍ","l":8,"ct":"word"},{"id":72000,"s":2,"a":102,"p":71,"t":"أَنفُسَهُمْ ۚ","c1":"ﮞﮟ","c2":"ﲎﲏ","l":9,"ct":"word"},{"id":72002,"s":2,"a":102,"p":72,"t":"لَوْ","c1":"ﮠ","c2":"ﲐ","l":9,"ct":"word"},{"id":72003,"s":2,"a":102,"p":73,"t":"كَانُوا۟","c1":"ﮡ","c2":"ﲑ","l":9,"ct":"word"},{"id":72004,"s":2,"a":102,"p":74,"t":"يَعْلَمُونَ","c1":"ﮢ","c2":"ﲒ","l":9,"ct":"word"},{"id":72005,"s":2,"a":102,"p":75,"t":"١٠٢","c1":"ﮣ","c2":"ﲓ","l":9,"ct":"end"},{"id":72290,"s":2,"a":103,"p":1,"t":"وَلَوْ","c1":"ﮤ","c2":"ﲔ","l":9,"ct":"word"},{"id":72291,"s":2,"a":103,"p":2,"t":"أَنَّهُمْ","c1":"ﮥ","c2":"ﲕ","l":9,"ct":"word"},{"id":72292,"s":2,"a":103,"p":3,"t":"ءَامَنُوا۟","c1":"ﮦ","c2":"ﲖ","l":9,"ct":"word"},{"id":72293,"s":2,"a":103,"p":4,"t":"وَٱتَّقَوْا۟","c1":"ﮧ","c2":"ﲗ","l":9,"ct":"word"},{"id":72294,"s":2,"a":103,"p":5,"t":"لَمَثُوبَةٌۭ","c1":"ﮨ","c2":"ﲘ","l":10,"ct":"word"},{"id":72295,"s":2,"a":103,"p":6,"t":"مِّنْ","c1":"ﮩ","c2":"ﲙ","l":10,"ct":"word"},{"id":72296,"s":2,"a":103,"p":7,"t":"عِندِ","c1":"ﮪ","c2":"ﲚ","l":10,"ct":"word"},{"id":72297,"s":2,"a":103,"p":8,"t":"ٱللَّهِ","c1":"ﮫ","c2":"ﲛ","l":10,"ct":"word"},{"id":72298,"s":2,"a":103,"p":9,"t":"خَيْرٌۭ ۖ","c1":"ﮬﮭ","c2":"ﲜﲝ","l":10,"ct":"word"},{"id":72300,"s":2,"a":103,"p":10,"t":"لَّوْ","c1":"ﮮ","c2":"ﲞ","l":10,"ct":"word"},{"id":72301,"s":2,"a":103,"p":11,"t":"كَانُوا۟","c1":"ﮯ","c2":"ﲟ","l":10,"ct":"word"},{"id":72302,"s":2,"a":103,"p":12,"t":"يَعْلَمُونَ","c1":"ﮰ","c2":"ﲠ","l":10,"ct":"word"},{"id":72303,"s":2,"a":103,"p":13,"t":"١٠٣","c1":"ﮱ","c2":"ﲡ","l":10,"ct":"end"},{"id":72457,"s":2,"a":104,"p":1,"t":"يَـٰٓأَيُّهَا","c1":"ﯓ","c2":"ﲢ","l":11,"ct":"word"},{"id":72458,"s":2,"a":104,"p":2,"t":"ٱلَّذِينَ","c1":"ﯔ","c2":"ﲣ","l":11,"ct":"word"},{"id":72459,"s":2,"a":104,"p":3,"t":"ءَامَنُوا۟","c1":"ﯕ","c2":"ﲤ","l":11,"ct":"word"},{"id":72460,"s":2,"a":104,"p":4,"t":"لَا","c1":"ﯖ","c2":"ﲥ","l":11,"ct":"word"},{"id":72461,"s":2,"a":104,"p":5,"t":"تَقُولُوا۟","c1":"ﯗ","c2":"ﲦ","l":11,"ct":"word"},{"id":72462,"s":2,"a":104,"p":6,"t":"رَٰعِنَا","c1":"ﯘ","c2":"ﲧ","l":11,"ct":"word"},{"id":72463,"s":2,"a":104,"p":7,"t":"وَقُولُوا۟","c1":"ﯙ","c2":"ﲨ","l":11,"ct":"word"},{"id":72464,"s":2,"a":104,"p":8,"t":"ٱنظُرْنَا","c1":"ﯚ","c2":"ﲩ","l":11,"ct":"word"},{"id":72465,"s":2,"a":104,"p":9,"t":"وَٱسْمَعُوا۟ ۗ","c1":"ﯛﯜ","c2":"ﲪﲫ","l":12,"ct":"word"},{"id":72467,"s":2,"a":104,"p":10,"t":"وَلِلْكَـٰفِرِينَ","c1":"ﯝ","c2":"ﲬ","l":12,"ct":"word"},{"id":72468,"s":2,"a":104,"p":11,"t":"عَذَابٌ","c1":"ﯞ","c2":"ﲭ","l":12,"ct":"word"},{"id":72469,"s":2,"a":104,"p":12,"t":"أَلِيمٌۭ","c1":"ﯟ","c2":"ﲮ","l":12,"ct":"word"},{"id":72470,"s":2,"a":104,"p":13,"t":"١٠٤","c1":"ﯠ","c2":"ﲯ","l":12,"ct":"end"},{"id":72882,"s":2,"a":105,"p":1,"t":"مَّا","c1":"ﯡ","c2":"ﲰ","l":12,"ct":"word"},{"id":72883,"s":2,"a":105,"p":2,"t":"يَوَدُّ","c1":"ﯢ","c2":"ﲱ","l":12,"ct":"word"},{"id":72884,"s":2,"a":105,"p":3,"t":"ٱلَّذِينَ","c1":"ﯣ","c2":"ﲲ","l":13,"ct":"word"},{"id":72885,"s":2,"a":105,"p":4,"t":"كَفَرُوا۟","c1":"ﯤ","c2":"ﲳ","l":13,"ct":"word"},{"id":72886,"s":2,"a":105,"p":5,"t":"مِنْ","c1":"ﯥ","c2":"ﲴ","l":13,"ct":"word"},{"id":72887,"s":2,"a":105,"p":6,"t":"أَهْلِ","c1":"ﯦ","c2":"ﲵ","l":13,"ct":"word"},{"id":72888,"s":2,"a":105,"p":7,"t":"ٱلْكِتَـٰبِ","c1":"ﯧ","c2":"ﲶ","l":13,"ct":"word"},{"id":72889,"s":2,"a":105,"p":8,"t":"وَلَا","c1":"ﯨ","c2":"ﲷ","l":13,"ct":"word"},{"id":72890,"s":2,"a":105,"p":9,"t":"ٱلْمُشْرِكِينَ","c1":"ﯩ","c2":"ﲸ","l":13,"ct":"word"},{"id":72891,"s":2,"a":105,"p":10,"t":"أَن","c1":"ﯪ","c2":"ﲹ","l":14,"ct":"word"},{"id":72892,"s":2,"a":105,"p":11,"t":"يُنَزَّلَ","c1":"ﯫ","c2":"ﲺ","l":14,"ct":"word"},{"id":72893,"s":2,"a":105,"p":12,"t":"عَلَيْكُم","c1":"ﯬ","c2":"ﲻ","l":14,"ct":"word"},{"id":72894,"s":2,"a":105,"p":13,"t":"مِّنْ","c1":"ﯭ","c2":"ﲼ","l":14,"ct":"word"},{"id":72895,"s":2,"a":105,"p":14,"t":"خَيْرٍۢ","c1":"ﯮ","c2":"ﲽ","l":14,"ct":"word"},{"id":72896,"s":2,"a":105,"p":15,"t":"مِّن","c1":"ﯯ","c2":"ﲾ","l":14,"ct":"word"},{"id":72897,"s":2,"a":105,"p":16,"t":"رَّبِّكُمْ ۗ","c1":"ﯰﯱ","c2":"ﲿﳀ","l":14,"ct":"word"},{"id":72899,"s":2,"a":105,"p":17,"t":"وَٱللَّهُ","c1":"ﯲ","c2":"ﳁ","l":14,"ct":"word"},{"id":72900,"s":2,"a":105,"p":18,"t":"يَخْتَصُّ","c1":"ﯳ","c2":"ﳂ","l":14,"ct":"word"},{"id":72901,"s":2,"a":105,"p":19,"t":"بِرَحْمَتِهِۦ","c1":"ﯴ","c2":"ﳃ","l":15,"ct":"word"},{"id":72902,"s":2,"a":105,"p":20,"t":"مَن","c1":"ﯵ","c2":"ﳄ","l":15,"ct":"word"},{"id":72903,"s":2,"a":105,"p":21,"t":"يَشَآءُ ۚ","c1":"ﯶﯷ","c2":"ﳅﳆ","l":15,"ct":"word"},{"id":72905,"s":2,"a":105,"p":22,"t":"وَٱللَّهُ","c1":"ﯸ","c2":"ﳇ","l":15,"ct":"word"},{"id":72906,"s":2,"a":105,"p":23,"t":"ذُو","c1":"ﯹ","c2":"ﳈ","l":15,"ct":"word"},{"id":72907,"s":2,"a":105,"p":24,"t":"ٱلْفَضْلِ","c1":"ﯺ","c2":"ﳉ","l":15,"ct":"word"},{"id":72908,"s":2,"a":105,"p":25,"t":"ٱلْعَظِيمِ","c1":"ﯻ","c2":"ﳊ","l":15,"ct":"word"},{"id":72909,"s":2,"a":105,"p":26,"t":"١٠٥","c1":"ﯼ","c2":"ﳋ","l":15,"ct":"end"}]