[{"id":14464,"s":32,"a":12,"p":1,"t":"وَلَوْ","c1":"ﭑ","c2":"ﱁ","l":1,"ct":"word"},{"id":14465,"s":32,"a":12,"p":2,"t":"تَرَىٰٓ","c1":"ﭒ","c2":"ﱂ","l":1,"ct":"word"},{"id":14466,"s":32,"a":12,"p":3,"t":"إِذِ","c1":"ﭓ","c2":"ﱃ","l":1,"ct":"word"},{"id":14467,"s":32,"a":12,"p":4,"t":"ٱلْمُجْرِمُونَ","c1":"ﭔ","c2":"ﱄ","l":1,"ct":"word"},{"id":14468,"s":32,"a":12,"p":5,"t":"نَاكِسُوا۟","c1":"ﭕ","c2":"ﱅ","l":1,"ct":"word"},{"id":14469,"s":32,"a":12,"p":6,"t":"رُءُوسِهِمْ","c1":"ﭖ","c2":"ﱆ","l":1,"ct":"word"},{"id":14470,"s":32,"a":12,"p":7,"t":"عِندَ","c1":"ﭗ","c2":"ﱇ","l":1,"ct":"word"},{"id":14471,"s":32,"a":12,"p":8,"t":"رَبِّهِمْ","c1":"ﭘ","c2":"ﱈ","l":1,"ct":"word"},{"id":14472,"s":32,"a":12,"p":9,"t":"رَبَّنَآ","c1":"ﭙ","c2":"ﱉ","l":2,"ct":"word"},{"id":14473,"s":32,"a":12,"p":10,"t":"أَبْصَرْنَا","c1":"ﭚ","c2":"ﱊ","l":2,"ct":"word"},{"id":14474,"s":32,"a":12,"p":11,"t":"وَسَمِعْنَا","c1":"ﭛ","c2":"ﱋ","l":2,"ct":"word"},{"id":14475,"s":32,"a":12,"p":12,"t":"فَٱرْجِعْنَا","c1":"ﭜ","c2":"ﱌ","l":2,"ct":"word"},{"id":14476,"s":32,"a":12,"p":13,"t":"نَعْمَلْ","c1":"ﭝ","c2":"ﱍ","l":2,"ct":"word"},{"id":14477,"s":32,"a":12,"p":14,"t":"صَـٰلِحًا","c1":"ﭞ","c2":"ﱎ","l":2,"ct":"word"},{"id":14478,"s":32,"a":12,"p":15,"t":"إِنَّا","c1":"ﭟ","c2":"ﱏ","l":2,"ct":"word"},{"id":14479,"s":32,"a":12,"p":16,"t":"مُوقِنُونَ","c1":"ﭠ","c2":"ﱐ","l":2,"ct":"word"},{"id":14480,"s":32,"a":12,"p":17,"t":"١٢","c1":"ﭡ","c2":"ﱑ","l":3,"ct":"end"},{"id":15570,"s":32,"a":13,"p":1,"t":"وَلَوْ","c1":"ﭢ","c2":"ﱒ","l":3,"ct":"word"},{"id":15571,"s":32,"a":13,"p":2,"t":"شِئْنَا","c1":"ﭣ","c2":"ﱓ","l":3,"ct":"word"},{"id":15572,"s":32,"a":13,"p":3,"t":"لَـَٔاتَيْنَا","c1":"ﭤ","c2":"ﱔ","l":3,"ct":"word"},{"id":15573,"s":32,"a":13,"p":4,"t":"كُلَّ","c1":"ﭥ","c2":"ﱕ","l":3,"ct":"word"},{"id":15574,"s":32,"a":13,"p":5,"t":"نَفْسٍ","c1":"ﭦ","c2":"ﱖ","l":3,"ct":"word"},{"id":15575,"s":32,"a":13,"p":6,"t":"هُدَىٰهَا","c1":"ﭧ","c2":"ﱗ","l":3,"ct":"word"},{"id":15576,"s":32,"a":13,"p":7,"t":"وَلَـٰكِنْ","c1":"ﭨ","c2":"ﱘ","l":3,"ct":"word"},{"id":15577,"s":32,"a":13,"p":8,"t":"حَقَّ","c1":"ﭩ","c2":"ﱙ","l":3,"ct":"word"},{"id":15578,"s":32,"a":13,"p":9,"t":"ٱلْقَوْلُ","c1":"ﭪ","c2":"ﱚ","l":4,"ct":"word"},{"id":15579,"s":32,"a":13,"p":10,"t":"مِنِّى","c1":"ﭫ","c2":"ﱛ","l":4,"ct":"word"},{"id":15580,"s":32,"a":13,"p":11,"t":"لَأَمْلَأَنَّ","c1":"ﭬ","c2":"ﱜ","l":4,"ct":"word"},{"id":15581,"s":32,"a":13,"p":12,"t":"جَهَنَّمَ","c1":"ﭭ","c2":"ﱝ","l":4,"ct":"word"},{"id":15582,"s":32,"a":13,"p":13,"t":"مِنَ","c1":"ﭮ","c2":"ﱞ","l":4,"ct":"word"},{"id":15583,"s":32,"a":13,"p":14,"t":"ٱلْجِنَّةِ","c1":"ﭯ","c2":"ﱟ","l":4,"ct":"word"},{"id":15584,"s":32,"a":13,"p":15,"t":"وَٱلنَّاسِ","c1":"ﭰ","c2":"ﱠ","l":4,"ct":"word"},{"id":15585,"s":32,"a":13,"p":16,"t":"أَجْمَعِينَ","c1":"ﭱ","c2":"ﱡ","l":4,"ct":"word"},{"id":15586,"s":32,"a":13,"p":17,"t":"١٣","c1":"ﭲ","c2":"ﱢ","l":5,"ct":"end"},{"id":16631,"s":32,"a":14,"p":1,"t":"فَذُوقُوا۟","c1":"ﭳ","c2":"ﱣ","l":5,"ct":"word"},{"id":16632,"s":32,"a":14,"p":2,"t":"بِمَا","c1":"ﭴ","c2":"ﱤ","l":5,"ct":"word"},{"id":16633,"s":32,"a":14,"p":3,"t":"نَسِيتُمْ","c1":"ﭵ","c2":"ﱥ","l":5,"ct":"word"},{"id":16634,"s":32,"a":14,"p":4,"t":"لِقَآءَ","c1":"ﭶ","c2":"ﱦ","l":5,"ct":"word"},{"id":16635,"s":32,"a":14,"p":5,"t":"يَوْمِكُمْ","c1":"ﭷ","c2":"ﱧ","l":5,"ct":"word"},{"id":16636,"s":32,"a":14,"p":6,"t":"هَـٰذَآ","c1":"ﭸ","c2":"ﱨ","l":5,"ct":"word"},{"id":16637,"s":32,"a":14,"p":7,"t":"إِنَّا","c1":"ﭹ","c2":"ﱩ","l":5,"ct":"word"},{"id":16638,"s":32,"a":14,"p":8,"t":"نَسِينَـٰكُمْ ۖ","c1":"ﭺﭻ","c2":"ﱪﱫ","l":5,"ct":"word"},{"id":16640,"s":32,"a":14,"p":9,"t":"وَذُوقُوا۟","c1":"ﭼ","c2":"ﱬ","l":6,"ct":"word"},{"id":16641,"s":32,"a":14,"p":10,"t":"عَذَابَ","c1":"ﭽ","c2":"ﱭ","l":6,"ct":"word"},{"id":16642,"s":32,"a":14,"p":11,"t":"ٱلْخُلْدِ","c1":"ﭾ","c2":"ﱮ","l":6,"ct":"word"},{"id":16643,"s":32,"a":14,"p":12,"t":"بِمَا","c1":"ﭿ","c2":"ﱯ","l":6,"ct":"word"},{"id":16644,"s":32,"a":14,"p":13,"t":"كُنتُمْ","c1":"ﮀ","c2":"ﱰ","l":6,"ct":"word"},{"id":16645,"s":32,"a":14,"p":14,"t":"تَعْمَلُونَ","c1":"ﮁ","c2":"ﱱ","l":6,"ct":"word"},{"id":16646,"s":32,"a":14,"p":15,"t":"١٤","c1":"ﮂ","c2":"ﱲ","l":6,"ct":"end"},{"id":17811,"s":32,"a":15,"p":1,"t":"إِنَّمَا","c1":"ﮃ","c2":"ﱳ","l":6,"ct":"word"},{"id":17812,"s":32,"a":15,"p":2,"t":"يُؤْمِنُ","c1":"ﮄ","c2":"ﱴ","l":6,"ct":"word"},{"id":17813,"s":32,"a":15,"p":3,"t":"بِـَٔايَـٰتِنَا","c1":"ﮅ","c2":"ﱵ","l":7,"ct":"word"},{"id":17814,"s":32,"a":15,"p":4,"t":"ٱلَّذِينَ","c1":"ﮆ","c2":"ﱶ","l":7,"ct":"word"},{"id":17815,"s":32,"a":15,"p":5,"t":"إِذَا","c1":"ﮇ","c2":"ﱷ","l":7,"ct":"word"},{"id":17816,"s":32,"a":15,"p":6,"t":"ذُكِّرُوا۟","c1":"ﮈ","c2":"ﱸ","l":7,"ct":"word"},{"id":17817,"s":32,"a":15,"p":7,"t":"بِهَا","c1":"ﮉ","c2":"ﱹ","l":7,"ct":"word"},{"id":17818,"s":32,"a":15,"p":8,"t":"خَرُّوا۟","c1":"ﮊ","c2":"ﱺﱻ","l":7,"ct":"word"},{"id":17819,"s":32,"a":15,"p":9,"t":"سُجَّدًۭا","c1":"ﮋ","c2":"ﱼﱽ","l":7,"ct":"word"},{"id":17820,"s":32,"a":15,"p":10,"t":"وَسَبَّحُوا۟","c1":"ﮌ","c2":"ﱾ","l":7,"ct":"word"},{"id":17821,"s":32,"a":15,"p":11,"t":"بِحَمْدِ","c1":"ﮍ","c2":"ﱿ","l":7,"ct":"word"},{"id":17822,"s":32,"a":15,"p":12,"t":"رَبِّهِمْ","c1":"ﮎ","c2":"ﲀ","l":8,"ct":"word"},{"id":17823,"s":32,"a":15,"p":13,"t":"وَهُمْ","c1":"ﮏ","c2":"ﲁ","l":8,"ct":"word"},{"id":17824,"s":32,"a":15,"p":14,"t":"لَا","c1":"ﮐ","c2":"ﲂ","l":8,"ct":"word"},{"id":17825,"s":32,"a":15,"p":15,"t":"يَسْتَكْبِرُونَ ۩","c1":"ﮑﮒ","c2":"ﲃﲄ","l":8,"ct":"word"},{"id":17827,"s":32,"a":15,"p":16,"t":"١٥","c1":"ﮓ","c2":"ﲅ","l":8,"ct":"end"},{"id":18856,"s":32,"a":16,"p":1,"t":"تَتَجَافَىٰ","c1":"ﮔ","c2":"ﲆ","l":8,"ct":"word"},{"id":18857,"s":32,"a":16,"p":2,"t":"جُنُوبُهُمْ","c1":"ﮕ","c2":"ﲇ","l":8,"ct":"word"},{"id":18858,"s":32,"a":16,"p":3,"t":"عَنِ","c1":"ﮖ","c2":"ﲈ","l":9,"ct":"word"},{"id":18859,"s":32,"a":16,"p":4,"t":"ٱلْمَضَاجِعِ","c1":"ﮗ","c2":"ﲉ","l":9,"ct":"word"},{"id":18860,"s":32,"a":16,"p":5,"t":"يَدْعُونَ","c1":"ﮘ","c2":"ﲊ","l":9,"ct":"word"},{"id":18861,"s":32,"a":16,"p":6,"t":"رَبَّهُمْ","c1":"ﮙ","c2":"ﲋ","l":9,"ct":"word"},{"id":18862,"s":32,"a":16,"p":7,"t":"خَوْفًۭا","c1":"ﮚ","c2":"ﲌ","l":9,"ct":"word"},{"id":18863,"s":32,"a":16,"p":8,"t":"وَطَمَعًۭا","c1":"ﮛ","c2":"ﲍ","l":9,"ct":"word"},{"id":18864,"s":32,"a":16,"p":9,"t":"وَمِمَّا","c1":"ﮜ","c2":"ﲎ","l":9,"ct":"word"},{"id":18865,"s":32,"a":16,"p":10,"t":"رَزَقْنَـٰهُمْ","c1":"ﮝ","c2":"ﲏ","l":9,"ct":"word"},{"id":18866,"s":32,"a":16,"p":11,"t":"يُنفِقُونَ","c1":"ﮞ","c2":"ﲐ","l":10,"ct":"word"},{"id":18867,"s":32,"a":16,"p":12,"t":"١٦","c1":"ﮟ","c2":"ﲑ","l":10,"ct":"end"},{"id":19947,"s":32,"a":17,"p":1,"t":"فَلَا","c1":"ﮠ","c2":"ﲒ","l":10,"ct":"word"},{"id":19948,"s":32,"a":17,"p":2,"t":"تَعْلَمُ","c1":"ﮡ","c2":"ﲓ","l":10,"ct":"word"},{"id":19949,"s":32,"a":17,"p":3,"t":"نَفْسٌۭ","c1":"ﮢ","c2":"ﲔ","l":10,"ct":"word"},{"id":19950,"s":32,"a":17,"p":4,"t":"مَّآ","c1":"ﮣ","c2":"ﲕ","l":10,"ct":"word"},{"id":19951,"s":32,"a":17,"p":5,"t":"أُخْفِىَ","c1":"ﮤ","c2":"ﲖ","l":10,"ct":"word"},{"id":19952,"s":32,"a":17,"p":6,"t":"لَهُم","c1":"ﮥ","c2":"ﲗ","l":10,"ct":"word"},{"id":19953,"s":32,"a":17,"p":7,"t":"مِّن","c1":"ﮦ","c2":"ﲘ","l":10,"ct":"word"},{"id":19954,"s":32,"a":17,"p":8,"t":"قُرَّةِ","c1":"ﮧ","c2":"ﲙ","l":10,"ct":"word"},{"id":19955,"s":32,"a":17,"p":9,"t":"أَعْيُنٍۢ","c1":"ﮨ","c2":"ﲚ","l":10,"ct":"word"},{"id":19956,"s":32,"a":17,"p":10,"t":"جَزَآءًۢ","c1":"ﮩ","c2":"ﲛ","l":11,"ct":"word"},{"id":19957,"s":32,"a":17,"p":11,"t":"بِمَا","c1":"ﮪ","c2":"ﲜ","l":11,"ct":"word"},{"id":19958,"s":32,"a":17,"p":12,"t":"كَانُوا۟","c1":"ﮫ","c2":"ﲝ","l":11,"ct":"word"},{"id":19959,"s":32,"a":17,"p":13,"t":"يَعْمَلُونَ","c1":"ﮬ","c2":"ﲞ","l":11,"ct":"word"},{"id":19960,"s":32,"a":17,"p":14,"t":"١٧","c1":"ﮭ","c2":"ﲟ","l":11,"ct":"end"},{"id":20954,"s":32,"a":18,"p":1,"t":"أَفَمَن","c1":"ﮮ","c2":"ﲠ","l":11,"ct":"word"},{"id":20955,"s":32,"a":18,"p":2,"t":"كَانَ","c1":"ﮯ","c2":"ﲡ","l":11,"ct":"word"},{"id":20956,"s":32,"a":18,"p":3,"t":"مُؤْمِنًۭا","c1":"ﮰ","c2":"ﲢ","l":11,"ct":"word"},{"id":20957,"s":32,"a":18,"p":4,"t":"كَمَن","c1":"ﮱ","c2":"ﲣ","l":11,"ct":"word"},{"id":20958,"s":32,"a":18,"p":5,"t":"كَانَ","c1":"ﯓ","c2":"ﲤ","l":11,"ct":"word"},{"id":20959,"s":32,"a":18,"p":6,"t":"فَاسِقًۭا ۚ","c1":"ﯔﯕ","c2":"ﲥﲦ","l":11,"ct":"word"},{"id":20961,"s":32,"a":18,"p":7,"t":"لَّا","c1":"ﯖ","c2":"ﲧ","l":12,"ct":"word"},{"id":20962,"s":32,"a":18,"p":8,"t":"يَسْتَوُۥنَ","c1":"ﯗ","c2":"ﲨ","l":12,"ct":"word"},{"id":20963,"s":32,"a":18,"p":9,"t":"١٨","c1":"ﯘ","c2":"ﲩ","l":12,"ct":"end"},{"id":22110,"s":32,"a":19,"p":1,"t":"أَمَّا","c1":"ﯙ","c2":"ﲪ","l":12,"ct":"word"},{"id":22111,"s":32,"a":19,"p":2,"t":"ٱلَّذِينَ","c1":"ﯚ","c2":"ﲫ","l":12,"ct":"word"},{"id":22112,"s":32,"a":19,"p":3,"t":"ءَامَنُوا۟","c1":"ﯛ","c2":"ﲬ","l":12,"ct":"word"},{"id":22113,"s":32,"a":19,"p":4,"t":"وَعَمِلُوا۟","c1":"ﯜ","c2":"ﲭ","l":12,"ct":"word"},{"id":22114,"s":32,"a":19,"p":5,"t":"ٱلصَّـٰلِحَـٰتِ","c1":"ﯝ","c2":"ﲮ","l":12,"ct":"word"},{"id":22115,"s":32,"a":19,"p":6,"t":"فَلَهُمْ","c1":"ﯞ","c2":"ﲯ","l":12,"ct":"word"},{"id":22116,"s":32,"a":19,"p":7,"t":"جَنَّـٰتُ","c1":"ﯟ","c2":"ﲰ","l":13,"ct":"word"},{"id":22117,"s":32,"a":19,"p":8,"t":"ٱلْمَأْوَىٰ","c1":"ﯠ","c2":"ﲱ","l":13,"ct":"word"},{"id":22118,"s":32,"a":19,"p":9,"t":"نُزُلًۢا","c1":"ﯡ","c2":"ﲲ","l":13,"ct":"word"},{"id":22119,"s":32,"a":19,"p":10,"t":"بِمَا","c1":"ﯢ","c2":"ﲳ","l":13,"ct":"word"},{"id":22120,"s":32,"a":19,"p":11,"t":"كَانُوا۟","c1":"ﯣ","c2":"ﲴ","l":13,"ct":"word"},{"id":22121,"s":32,"a":19,"p":12,"t":"يَعْمَلُونَ","c1":"ﯤ","c2":"ﲵ","l":13,"ct":"word"},{"id":22122,"s":32,"a":19,"p":13,"t":"١٩","c1":"ﯥ","c2":"ﲶ","l":13,"ct":"end"},{"id":23166,"s":32,"a":20,"p":1,"t":"وَأَمَّا","c1":"ﯦ","c2":"ﲷ","l":13,"ct":"word"},{"id":23167,"s":32,"a":20,"p":2,"t":"ٱلَّذِينَ","c1":"ﯧ","c2":"ﲸ","l":13,"ct":"word"},{"id":23168,"s":32,"a":20,"p":3,"t":"فَسَقُوا۟","c1":"ﯨ","c2":"ﲹ","l":13,"ct":"word"},{"id":23169,"s":32,"a":20,"p":4,"t":"فَمَأْوَىٰهُمُ","c1":"ﯩ","c2":"ﲺ","l":14,"ct":"word"},{"id":23170,"s":32,"a":20,"p":5,"t":"ٱلنَّارُ ۖ","c1":"ﯪﯫ","c2":"ﲻﲼ","l":14,"ct":"word"},{"id":23172,"s":32,"a":20,"p":6,"t":"كُلَّمَآ","c1":"ﯬ","c2":"ﲽ","l":14,"ct":"word"},{"id":23173,"s":32,"a":20,"p":7,"t":"أَرَادُوٓا۟","c1":"ﯭ","c2":"ﲾ","l":14,"ct":"word"},{"id":23174,"s":32,"a":20,"p":8,"t":"أَن","c1":"ﯮ","c2":"ﲿ","l":14,"ct":"word"},{"id":23175,"s":32,"a":20,"p":9,"t":"يَخْرُجُوا۟","c1":"ﯯ","c2":"ﳀ","l":14,"ct":"word"},{"id":23176,"s":32,"a":20,"p":10,"t":"مِنْهَآ","c1":"ﯰ","c2":"ﳁ","l":14,"ct":"word"},{"id":23177,"s":32,"a":20,"p":11,"t":"أُعِيدُوا۟","c1":"ﯱ","c2":"ﳂ","l":14,"ct":"word"},{"id":23178,"s":32,"a":20,"p":12,"t":"فِيهَا","c1":"ﯲ","c2":"ﳃ","l":14,"ct":"word"},{"id":23179,"s":32,"a":20,"p":13,"t":"وَقِيلَ","c1":"ﯳ","c2":"ﳄ","l":15,"ct":"word"},{"id":23180,"s":32,"a":20,"p":14,"t":"لَهُمْ","c1":"ﯴ","c2":"ﳅ","l":15,"ct":"word"},{"id":23181,"s":32,"a":20,"p":15,"t":"ذُوقُوا۟","c1":"ﯵ","c2":"ﳆ","l":15,"ct":"word"},{"id":23182,"s":32,"a":20,"p":16,"t":"عَذَابَ","c1":"ﯶ","c2":"ﳇ","l":15,"ct":"word"},{"id":23183,"s":32,"a":20,"p":17,"t":"ٱلنَّارِ","c1":"ﯷ","c2":"ﳈ","l":15,"ct":"word"},{"id":23184,"s":32,"a":20,"p":18,"t":"ٱلَّذِى","c1":"ﯸ","c2":"ﳉ","l":15,"ct":"word"},{"id":23185,"s":32,"a":20,"p":19,"t":"كُنتُم","c1":"ﯹ","c2":"ﳊ","l":15,"ct":"word"},{"id":23186,"s":32,"a":20,"p":20,"t":"بِهِۦ","c1":"ﯺ","c2":"ﳋ","l":15,"ct":"word"},{"id":23187,"s":32,"a":20,"p":21,"t":"تُكَذِّبُونَ","c1":"ﯻ","c2":"ﳌ","l":15,"ct":"word"},{"id":23188,"s":32,"a":20,"p":22,"t":"٢٠","c1":"ﯼ","c2":"ﳍ","l":15,"ct":"end"}]