[{"id":18449,"s":3,"a":16,"p":1,"t":"ٱلَّذِينَ","c1":"ﭑ","c2":"ﱁ","l":1,"ct":"word"},{"id":18450,"s":3,"a":16,"p":2,"t":"يَقُولُونَ","c1":"ﭒ","c2":"ﱂ","l":1,"ct":"word"},{"id":18451,"s":3,"a":16,"p":3,"t":"رَبَّنَآ","c1":"ﭓ","c2":"ﱃ","l":1,"ct":"word"},{"id":18452,"s":3,"a":16,"p":4,"t":"إِنَّنَآ","c1":"ﭔ","c2":"ﱄ","l":1,"ct":"word"},{"id":18453,"s":3,"a":16,"p":5,"t":"ءَامَنَّا","c1":"ﭕ","c2":"ﱅ","l":1,"ct":"word"},{"id":18454,"s":3,"a":16,"p":6,"t":"فَٱغْفِرْ","c1":"ﭖ","c2":"ﱆ","l":1,"ct":"word"},{"id":18455,"s":3,"a":16,"p":7,"t":"لَنَا","c1":"ﭗ","c2":"ﱇ","l":1,"ct":"word"},{"id":18456,"s":3,"a":16,"p":8,"t":"ذُنُوبَنَا","c1":"ﭘ","c2":"ﱈ","l":1,"ct":"word"},{"id":18457,"s":3,"a":16,"p":9,"t":"وَقِنَا","c1":"ﭙ","c2":"ﱉ","l":2,"ct":"word"},{"id":18458,"s":3,"a":16,"p":10,"t":"عَذَابَ","c1":"ﭚ","c2":"ﱊ","l":2,"ct":"word"},{"id":18459,"s":3,"a":16,"p":11,"t":"ٱلنَّارِ","c1":"ﭛ","c2":"ﱋ","l":2,"ct":"word"},{"id":18460,"s":3,"a":16,"p":12,"t":"١٦","c1":"ﭜ","c2":"ﱌ","l":2,"ct":"end"},{"id":19434,"s":3,"a":17,"p":1,"t":"ٱلصَّـٰبِرِينَ","c1":"ﭝ","c2":"ﱍ","l":2,"ct":"word"},{"id":19435,"s":3,"a":17,"p":2,"t":"وَٱلصَّـٰدِقِينَ","c1":"ﭞ","c2":"ﱎ","l":2,"ct":"word"},{"id":19436,"s":3,"a":17,"p":3,"t":"وَٱلْقَـٰنِتِينَ","c1":"ﭟ","c2":"ﱏ","l":2,"ct":"word"},{"id":19437,"s":3,"a":17,"p":4,"t":"وَٱلْمُنفِقِينَ","c1":"ﭠ","c2":"ﱐ","l":3,"ct":"word"},{"id":19438,"s":3,"a":17,"p":5,"t":"وَٱلْمُسْتَغْفِرِينَ","c1":"ﭡ","c2":"ﱑ","l":3,"ct":"word"},{"id":19439,"s":3,"a":17,"p":6,"t":"بِٱلْأَسْحَارِ","c1":"ﭢ","c2":"ﱒ","l":3,"ct":"word"},{"id":19440,"s":3,"a":17,"p":7,"t":"١٧","c1":"ﭣ","c2":"ﱓ","l":3,"ct":"end"},{"id":20519,"s":3,"a":18,"p":1,"t":"شَهِدَ","c1":"ﭤ","c2":"ﱔ","l":3,"ct":"word"},{"id":20520,"s":3,"a":18,"p":2,"t":"ٱللَّهُ","c1":"ﭥ","c2":"ﱕ","l":3,"ct":"word"},{"id":20521,"s":3,"a":18,"p":3,"t":"أَنَّهُۥ","c1":"ﭦ","c2":"ﱖ","l":4,"ct":"word"},{"id":20522,"s":3,"a":18,"p":4,"t":"لَآ","c1":"ﭧ","c2":"ﱗ","l":4,"ct":"word"},{"id":20523,"s":3,"a":18,"p":5,"t":"إِلَـٰهَ","c1":"ﭨ","c2":"ﱘ","l":4,"ct":"word"},{"id":20524,"s":3,"a":18,"p":6,"t":"إِلَّا","c1":"ﭩ","c2":"ﱙ","l":4,"ct":"word"},{"id":20525,"s":3,"a":18,"p":7,"t":"هُوَ","c1":"ﭪ","c2":"ﱚ","l":4,"ct":"word"},{"id":20526,"s":3,"a":18,"p":8,"t":"وَٱلْمَلَـٰٓئِكَةُ","c1":"ﭫ","c2":"ﱛ","l":4,"ct":"word"},{"id":20527,"s":3,"a":18,"p":9,"t":"وَأُو۟لُوا۟","c1":"ﭬ","c2":"ﱜ","l":4,"ct":"word"},{"id":20528,"s":3,"a":18,"p":10,"t":"ٱلْعِلْمِ","c1":"ﭭ","c2":"ﱝ","l":4,"ct":"word"},{"id":20529,"s":3,"a":18,"p":11,"t":"قَآئِمًۢا","c1":"ﭮ","c2":"ﱞ","l":4,"ct":"word"},{"id":20530,"s":3,"a":18,"p":12,"t":"بِٱلْقِسْطِ ۚ","c1":"ﭯﭰ","c2":"ﱟﱠ","l":5,"ct":"word"},{"id":20532,"s":3,"a":18,"p":13,"t":"لَآ","c1":"ﭱ","c2":"ﱡ","l":5,"ct":"word"},{"id":20533,"s":3,"a":18,"p":14,"t":"إِلَـٰهَ","c1":"ﭲ","c2":"ﱢ","l":5,"ct":"word"},{"id":20534,"s":3,"a":18,"p":15,"t":"إِلَّا","c1":"ﭳ","c2":"ﱣ","l":5,"ct":"word"},{"id":20535,"s":3,"a":18,"p":16,"t":"هُوَ","c1":"ﭴ","c2":"ﱤ","l":5,"ct":"word"},{"id":20536,"s":3,"a":18,"p":17,"t":"ٱلْعَزِيزُ","c1":"ﭵ","c2":"ﱥ","l":5,"ct":"word"},{"id":20537,"s":3,"a":18,"p":18,"t":"ٱلْحَكِيمُ","c1":"ﭶ","c2":"ﱦ","l":5,"ct":"word"},{"id":20538,"s":3,"a":18,"p":19,"t":"١٨","c1":"ﭷ","c2":"ﱧ","l":5,"ct":"end"},{"id":21588,"s":3,"a":19,"p":1,"t":"إِنَّ","c1":"ﭸ","c2":"ﱨ","l":5,"ct":"word"},{"id":21589,"s":3,"a":19,"p":2,"t":"ٱلدِّينَ","c1":"ﭹ","c2":"ﱩ","l":5,"ct":"word"},{"id":21590,"s":3,"a":19,"p":3,"t":"عِندَ","c1":"ﭺ","c2":"ﱪ","l":6,"ct":"word"},{"id":21591,"s":3,"a":19,"p":4,"t":"ٱللَّهِ","c1":"ﭻ","c2":"ﱫ","l":6,"ct":"word"},{"id":21592,"s":3,"a":19,"p":5,"t":"ٱلْإِسْلَـٰمُ ۗ","c1":"ﭼﭽ","c2":"ﱬﱭ","l":6,"ct":"word"},{"id":21594,"s":3,"a":19,"p":6,"t":"وَمَا","c1":"ﭾ","c2":"ﱮ","l":6,"ct":"word"},{"id":21595,"s":3,"a":19,"p":7,"t":"ٱخْتَلَفَ","c1":"ﭿ","c2":"ﱯ","l":6,"ct":"word"},{"id":21596,"s":3,"a":19,"p":8,"t":"ٱلَّذِينَ","c1":"ﮀ","c2":"ﱰ","l":6,"ct":"word"},{"id":21597,"s":3,"a":19,"p":9,"t":"أُوتُوا۟","c1":"ﮁ","c2":"ﱱ","l":6,"ct":"word"},{"id":21598,"s":3,"a":19,"p":10,"t":"ٱلْكِتَـٰبَ","c1":"ﮂ","c2":"ﱲ","l":6,"ct":"word"},{"id":21599,"s":3,"a":19,"p":11,"t":"إِلَّا","c1":"ﮃ","c2":"ﱳ","l":7,"ct":"word"},{"id":21600,"s":3,"a":19,"p":12,"t":"مِنۢ","c1":"ﮄ","c2":"ﱴ","l":7,"ct":"word"},{"id":21601,"s":3,"a":19,"p":13,"t":"بَعْدِ","c1":"ﮅ","c2":"ﱵ","l":7,"ct":"word"},{"id":21602,"s":3,"a":19,"p":14,"t":"مَا","c1":"ﮆ","c2":"ﱶ","l":7,"ct":"word"},{"id":21603,"s":3,"a":19,"p":15,"t":"جَآءَهُمُ","c1":"ﮇ","c2":"ﱷ","l":7,"ct":"word"},{"id":21604,"s":3,"a":19,"p":16,"t":"ٱلْعِلْمُ","c1":"ﮈ","c2":"ﱸ","l":7,"ct":"word"},{"id":21605,"s":3,"a":19,"p":17,"t":"بَغْيًۢا","c1":"ﮉ","c2":"ﱹ","l":7,"ct":"word"},{"id":21606,"s":3,"a":19,"p":18,"t":"بَيْنَهُمْ ۗ","c1":"ﮊﮋ","c2":"ﱺﱻ","l":7,"ct":"word"},{"id":21608,"s":3,"a":19,"p":19,"t":"وَمَن","c1":"ﮌ","c2":"ﱼ","l":7,"ct":"word"},{"id":21609,"s":3,"a":19,"p":20,"t":"يَكْفُرْ","c1":"ﮍ","c2":"ﱽ","l":7,"ct":"word"},{"id":21610,"s":3,"a":19,"p":21,"t":"بِـَٔايَـٰتِ","c1":"ﮎ","c2":"ﱾ","l":8,"ct":"word"},{"id":21611,"s":3,"a":19,"p":22,"t":"ٱللَّهِ","c1":"ﮏ","c2":"ﱿ","l":8,"ct":"word"},{"id":21612,"s":3,"a":19,"p":23,"t":"فَإِنَّ","c1":"ﮐ","c2":"ﲀ","l":8,"ct":"word"},{"id":21613,"s":3,"a":19,"p":24,"t":"ٱللَّهَ","c1":"ﮑ","c2":"ﲁ","l":8,"ct":"word"},{"id":21614,"s":3,"a":19,"p":25,"t":"سَرِيعُ","c1":"ﮒ","c2":"ﲂ","l":8,"ct":"word"},{"id":21615,"s":3,"a":19,"p":26,"t":"ٱلْحِسَابِ","c1":"ﮓ","c2":"ﲃ","l":8,"ct":"word"},{"id":21616,"s":3,"a":19,"p":27,"t":"١٩","c1":"ﮔ","c2":"ﲄ","l":8,"ct":"end"},{"id":22702,"s":3,"a":20,"p":1,"t":"فَإِنْ","c1":"ﮕ","c2":"ﲅ","l":8,"ct":"word"},{"id":22703,"s":3,"a":20,"p":2,"t":"حَآجُّوكَ","c1":"ﮖ","c2":"ﲆ","l":8,"ct":"word"},{"id":22704,"s":3,"a":20,"p":3,"t":"فَقُلْ","c1":"ﮗ","c2":"ﲇ","l":9,"ct":"word"},{"id":22705,"s":3,"a":20,"p":4,"t":"أَسْلَمْتُ","c1":"ﮘ","c2":"ﲈ","l":9,"ct":"word"},{"id":22706,"s":3,"a":20,"p":5,"t":"وَجْهِىَ","c1":"ﮙ","c2":"ﲉ","l":9,"ct":"word"},{"id":22707,"s":3,"a":20,"p":6,"t":"لِلَّهِ","c1":"ﮚ","c2":"ﲊ","l":9,"ct":"word"},{"id":22708,"s":3,"a":20,"p":7,"t":"وَمَنِ","c1":"ﮛ","c2":"ﲋ","l":9,"ct":"word"},{"id":22709,"s":3,"a":20,"p":8,"t":"ٱتَّبَعَنِ ۗ","c1":"ﮜﮝ","c2":"ﲌﲍ","l":9,"ct":"word"},{"id":22711,"s":3,"a":20,"p":9,"t":"وَقُل","c1":"ﮞ","c2":"ﲎ","l":9,"ct":"word"},{"id":22712,"s":3,"a":20,"p":10,"t":"لِّلَّذِينَ","c1":"ﮟ","c2":"ﲏ","l":9,"ct":"word"},{"id":22713,"s":3,"a":20,"p":11,"t":"أُوتُوا۟","c1":"ﮠ","c2":"ﲐ","l":9,"ct":"word"},{"id":22714,"s":3,"a":20,"p":12,"t":"ٱلْكِتَـٰبَ","c1":"ﮡ","c2":"ﲑ","l":10,"ct":"word"},{"id":22715,"s":3,"a":20,"p":13,"t":"وَٱلْأُمِّيِّـۧنَ","c1":"ﮢ","c2":"ﲒ","l":10,"ct":"word"},{"id":22716,"s":3,"a":20,"p":14,"t":"ءَأَسْلَمْتُمْ ۚ","c1":"ﮣﮤ","c2":"ﲓﲔ","l":10,"ct":"word"},{"id":22718,"s":3,"a":20,"p":15,"t":"فَإِنْ","c1":"ﮥ","c2":"ﲕ","l":10,"ct":"word"},{"id":22719,"s":3,"a":20,"p":16,"t":"أَسْلَمُوا۟","c1":"ﮦ","c2":"ﲖ","l":10,"ct":"word"},{"id":22720,"s":3,"a":20,"p":17,"t":"فَقَدِ","c1":"ﮧ","c2":"ﲗ","l":10,"ct":"word"},{"id":22721,"s":3,"a":20,"p":18,"t":"ٱهْتَدَوا۟ ۖ","c1":"ﮨﮩ","c2":"ﲘﲙ","l":10,"ct":"word"},{"id":22723,"s":3,"a":20,"p":19,"t":"وَّإِن","c1":"ﮪ","c2":"ﲚ","l":11,"ct":"word"},{"id":22724,"s":3,"a":20,"p":20,"t":"تَوَلَّوْا۟","c1":"ﮫ","c2":"ﲛ","l":11,"ct":"word"},{"id":22725,"s":3,"a":20,"p":21,"t":"فَإِنَّمَا","c1":"ﮬ","c2":"ﲜ","l":11,"ct":"word"},{"id":22726,"s":3,"a":20,"p":22,"t":"عَلَيْكَ","c1":"ﮭ","c2":"ﲝ","l":11,"ct":"word"},{"id":22727,"s":3,"a":20,"p":23,"t":"ٱلْبَلَـٰغُ ۗ","c1":"ﮮﮯ","c2":"ﲞﲟ","l":11,"ct":"word"},{"id":22729,"s":3,"a":20,"p":24,"t":"وَٱللَّهُ","c1":"ﮰ","c2":"ﲠ","l":11,"ct":"word"},{"id":22730,"s":3,"a":20,"p":25,"t":"بَصِيرٌۢ","c1":"ﮱ","c2":"ﲡ","l":11,"ct":"word"},{"id":22731,"s":3,"a":20,"p":26,"t":"بِٱلْعِبَادِ","c1":"ﯓ","c2":"ﲢ","l":11,"ct":"word"},{"id":22732,"s":3,"a":20,"p":27,"t":"٢٠","c1":"ﯔ","c2":"ﲣ","l":11,"ct":"end"},{"id":23839,"s":3,"a":21,"p":1,"t":"إِنَّ","c1":"ﯕ","c2":"ﲤ","l":12,"ct":"word"},{"id":23840,"s":3,"a":21,"p":2,"t":"ٱلَّذِينَ","c1":"ﯖ","c2":"ﲥ","l":12,"ct":"word"},{"id":23841,"s":3,"a":21,"p":3,"t":"يَكْفُرُونَ","c1":"ﯗ","c2":"ﲦ","l":12,"ct":"word"},{"id":23842,"s":3,"a":21,"p":4,"t":"بِـَٔايَـٰتِ","c1":"ﯘ","c2":"ﲧ","l":12,"ct":"word"},{"id":23843,"s":3,"a":21,"p":5,"t":"ٱللَّهِ","c1":"ﯙ","c2":"ﲨ","l":12,"ct":"word"},{"id":23844,"s":3,"a":21,"p":6,"t":"وَيَقْتُلُونَ","c1":"ﯚ","c2":"ﲩ","l":12,"ct":"word"},{"id":23845,"s":3,"a":21,"p":7,"t":"ٱلنَّبِيِّـۧنَ","c1":"ﯛ","c2":"ﲪ","l":12,"ct":"word"},{"id":23846,"s":3,"a":21,"p":8,"t":"بِغَيْرِ","c1":"ﯜ","c2":"ﲫ","l":13,"ct":"word"},{"id":23847,"s":3,"a":21,"p":9,"t":"حَقٍّۢ","c1":"ﯝ","c2":"ﲬ","l":13,"ct":"word"},{"id":23848,"s":3,"a":21,"p":10,"t":"وَيَقْتُلُونَ","c1":"ﯞ","c2":"ﲭ","l":13,"ct":"word"},{"id":23849,"s":3,"a":21,"p":11,"t":"ٱلَّذِينَ","c1":"ﯟ","c2":"ﲮ","l":13,"ct":"word"},{"id":23850,"s":3,"a":21,"p":12,"t":"يَأْمُرُونَ","c1":"ﯠ","c2":"ﲯ","l":13,"ct":"word"},{"id":23851,"s":3,"a":21,"p":13,"t":"بِٱلْقِسْطِ","c1":"ﯡ","c2":"ﲰ","l":13,"ct":"word"},{"id":23852,"s":3,"a":21,"p":14,"t":"مِنَ","c1":"ﯢ","c2":"ﲱ","l":13,"ct":"word"},{"id":23853,"s":3,"a":21,"p":15,"t":"ٱلنَّاسِ","c1":"ﯣ","c2":"ﲲ","l":14,"ct":"word"},{"id":23854,"s":3,"a":21,"p":16,"t":"فَبَشِّرْهُم","c1":"ﯤ","c2":"ﲳ","l":14,"ct":"word"},{"id":23855,"s":3,"a":21,"p":17,"t":"بِعَذَابٍ","c1":"ﯥ","c2":"ﲴ","l":14,"ct":"word"},{"id":23856,"s":3,"a":21,"p":18,"t":"أَلِيمٍ","c1":"ﯦ","c2":"ﲵ","l":14,"ct":"word"},{"id":23857,"s":3,"a":21,"p":19,"t":"٢١","c1":"ﯧ","c2":"ﲶ","l":14,"ct":"end"},{"id":24633,"s":3,"a":22,"p":1,"t":"أُو۟لَـٰٓئِكَ","c1":"ﯨ","c2":"ﲷ","l":14,"ct":"word"},{"id":24634,"s":3,"a":22,"p":2,"t":"ٱلَّذِينَ","c1":"ﯩ","c2":"ﲸ","l":14,"ct":"word"},{"id":24635,"s":3,"a":22,"p":3,"t":"حَبِطَتْ","c1":"ﯪ","c2":"ﲹ","l":14,"ct":"word"},{"id":24636,"s":3,"a":22,"p":4,"t":"أَعْمَـٰلُهُمْ","c1":"ﯫ","c2":"ﲺ","l":15,"ct":"word"},{"id":24637,"s":3,"a":22,"p":5,"t":"فِى","c1":"ﯬ","c2":"ﲻ","l":15,"ct":"word"},{"id":24638,"s":3,"a":22,"p":6,"t":"ٱلدُّنْيَا","c1":"ﯭ","c2":"ﲼ","l":15,"ct":"word"},{"id":24639,"s":3,"a":22,"p":7,"t":"وَٱلْـَٔاخِرَةِ","c1":"ﯮ","c2":"ﲽ","l":15,"ct":"word"},{"id":24640,"s":3,"a":22,"p":8,"t":"وَمَا","c1":"ﯯ","c2":"ﲾ","l":15,"ct":"word"},{"id":24641,"s":3,"a":22,"p":9,"t":"لَهُم","c1":"ﯰ","c2":"ﲿ","l":15,"ct":"word"},{"id":24642,"s":3,"a":22,"p":10,"t":"مِّن","c1":"ﯱ","c2":"ﳀ","l":15,"ct":"word"},{"id":24643,"s":3,"a":22,"p":11,"t":"نَّـٰصِرِينَ","c1":"ﯲ","c2":"ﳁ","l":15,"ct":"word"},{"id":24644,"s":3,"a":22,"p":12,"t":"٢٢","c1":"ﯳ","c2":"ﳂ","l":15,"ct":"end"}]