[{"id":22464,"s":47,"a":20,"p":1,"t":"وَيَقُولُ","c1":"ﭑ","c2":"ﱁ","l":1,"ct":"word"},{"id":22465,"s":47,"a":20,"p":2,"t":"ٱلَّذِينَ","c1":"ﭒ","c2":"ﱂ","l":1,"ct":"word"},{"id":22466,"s":47,"a":20,"p":3,"t":"ءَامَنُوا۟","c1":"ﭓ","c2":"ﱃ","l":1,"ct":"word"},{"id":22467,"s":47,"a":20,"p":4,"t":"لَوْلَا","c1":"ﭔ","c2":"ﱄ","l":1,"ct":"word"},{"id":22468,"s":47,"a":20,"p":5,"t":"نُزِّلَتْ","c1":"ﭕ","c2":"ﱅ","l":1,"ct":"word"},{"id":22469,"s":47,"a":20,"p":6,"t":"سُورَةٌۭ ۖ","c1":"ﭖﭗ","c2":"ﱆﱇ","l":1,"ct":"word"},{"id":22471,"s":47,"a":20,"p":7,"t":"فَإِذَآ","c1":"ﭘ","c2":"ﱈ","l":1,"ct":"word"},{"id":22472,"s":47,"a":20,"p":8,"t":"أُنزِلَتْ","c1":"ﭙ","c2":"ﱉ","l":1,"ct":"word"},{"id":22473,"s":47,"a":20,"p":9,"t":"سُورَةٌۭ","c1":"ﭚ","c2":"ﱊ","l":1,"ct":"word"},{"id":22474,"s":47,"a":20,"p":10,"t":"مُّحْكَمَةٌۭ","c1":"ﭛ","c2":"ﱋ","l":2,"ct":"word"},{"id":22475,"s":47,"a":20,"p":11,"t":"وَذُكِرَ","c1":"ﭜ","c2":"ﱌ","l":2,"ct":"word"},{"id":22476,"s":47,"a":20,"p":12,"t":"فِيهَا","c1":"ﭝ","c2":"ﱍ","l":2,"ct":"word"},{"id":22477,"s":47,"a":20,"p":13,"t":"ٱلْقِتَالُ ۙ","c1":"ﭞﭟ","c2":"ﱎ","l":2,"ct":"word"},{"id":22479,"s":47,"a":20,"p":14,"t":"رَأَيْتَ","c1":"ﭠ","c2":"ﱏ","l":2,"ct":"word"},{"id":22480,"s":47,"a":20,"p":15,"t":"ٱلَّذِينَ","c1":"ﭡ","c2":"ﱐ","l":2,"ct":"word"},{"id":22481,"s":47,"a":20,"p":16,"t":"فِى","c1":"ﭢ","c2":"ﱑ","l":2,"ct":"word"},{"id":22482,"s":47,"a":20,"p":17,"t":"قُلُوبِهِم","c1":"ﭣ","c2":"ﱒ","l":2,"ct":"word"},{"id":22483,"s":47,"a":20,"p":18,"t":"مَّرَضٌۭ","c1":"ﭤ","c2":"ﱓ","l":2,"ct":"word"},{"id":22484,"s":47,"a":20,"p":19,"t":"يَنظُرُونَ","c1":"ﭥ","c2":"ﱔ","l":3,"ct":"word"},{"id":22485,"s":47,"a":20,"p":20,"t":"إِلَيْكَ","c1":"ﭦ","c2":"ﱕ","l":3,"ct":"word"},{"id":22486,"s":47,"a":20,"p":21,"t":"نَظَرَ","c1":"ﭧ","c2":"ﱖ","l":3,"ct":"word"},{"id":22487,"s":47,"a":20,"p":22,"t":"ٱلْمَغْشِىِّ","c1":"ﭨ","c2":"ﱗ","l":3,"ct":"word"},{"id":22488,"s":47,"a":20,"p":23,"t":"عَلَيْهِ","c1":"ﭩ","c2":"ﱘ","l":3,"ct":"word"},{"id":22489,"s":47,"a":20,"p":24,"t":"مِنَ","c1":"ﭪ","c2":"ﱙ","l":3,"ct":"word"},{"id":22490,"s":47,"a":20,"p":25,"t":"ٱلْمَوْتِ ۖ","c1":"ﭫﭬ","c2":"ﱚﱛ","l":3,"ct":"word"},{"id":22492,"s":47,"a":20,"p":26,"t":"فَأَوْلَىٰ","c1":"ﭭ","c2":"ﱜ","l":3,"ct":"word"},{"id":22493,"s":47,"a":20,"p":27,"t":"لَهُمْ","c1":"ﭮ","c2":"ﱝ","l":3,"ct":"word"},{"id":22494,"s":47,"a":20,"p":28,"t":"٢٠","c1":"ﭯ","c2":"ﱞ","l":4,"ct":"end"},{"id":23624,"s":47,"a":21,"p":1,"t":"طَاعَةٌۭ","c1":"ﭰ","c2":"ﱟ","l":4,"ct":"word"},{"id":23625,"s":47,"a":21,"p":2,"t":"وَقَوْلٌۭ","c1":"ﭱ","c2":"ﱠ","l":4,"ct":"word"},{"id":23626,"s":47,"a":21,"p":3,"t":"مَّعْرُوفٌۭ ۚ","c1":"ﭲﭳ","c2":"ﱡﱢ","l":4,"ct":"word"},{"id":23628,"s":47,"a":21,"p":4,"t":"فَإِذَا","c1":"ﭴ","c2":"ﱣ","l":4,"ct":"word"},{"id":23629,"s":47,"a":21,"p":5,"t":"عَزَمَ","c1":"ﭵ","c2":"ﱤ","l":4,"ct":"word"},{"id":23630,"s":47,"a":21,"p":6,"t":"ٱلْأَمْرُ","c1":"ﭶ","c2":"ﱥ","l":4,"ct":"word"},{"id":23631,"s":47,"a":21,"p":7,"t":"فَلَوْ","c1":"ﭷ","c2":"ﱦ","l":4,"ct":"word"},{"id":23632,"s":47,"a":21,"p":8,"t":"صَدَقُوا۟","c1":"ﭸ","c2":"ﱧ","l":4,"ct":"word"},{"id":23633,"s":47,"a":21,"p":9,"t":"ٱللَّهَ","c1":"ﭹ","c2":"ﱨ","l":4,"ct":"word"},{"id":23634,"s":47,"a":21,"p":10,"t":"لَكَانَ","c1":"ﭺ","c2":"ﱩ","l":5,"ct":"word"},{"id":23635,"s":47,"a":21,"p":11,"t":"خَيْرًۭا","c1":"ﭻ","c2":"ﱪ","l":5,"ct":"word"},{"id":23636,"s":47,"a":21,"p":12,"t":"لَّهُمْ","c1":"ﭼ","c2":"ﱫ","l":5,"ct":"word"},{"id":23637,"s":47,"a":21,"p":13,"t":"٢١","c1":"ﭽ","c2":"ﱬ","l":5,"ct":"end"},{"id":24602,"s":47,"a":22,"p":1,"t":"فَهَلْ","c1":"ﭾ","c2":"ﱭ","l":5,"ct":"word"},{"id":24603,"s":47,"a":22,"p":2,"t":"عَسَيْتُمْ","c1":"ﭿ","c2":"ﱮ","l":5,"ct":"word"},{"id":24604,"s":47,"a":22,"p":3,"t":"إِن","c1":"ﮀ","c2":"ﱯ","l":5,"ct":"word"},{"id":24605,"s":47,"a":22,"p":4,"t":"تَوَلَّيْتُمْ","c1":"ﮁ","c2":"ﱰ","l":5,"ct":"word"},{"id":24606,"s":47,"a":22,"p":5,"t":"أَن","c1":"ﮂ","c2":"ﱱ","l":5,"ct":"word"},{"id":24607,"s":47,"a":22,"p":6,"t":"تُفْسِدُوا۟","c1":"ﮃ","c2":"ﱲ","l":5,"ct":"word"},{"id":24608,"s":47,"a":22,"p":7,"t":"فِى","c1":"ﮄ","c2":"ﱳ","l":6,"ct":"word"},{"id":24609,"s":47,"a":22,"p":8,"t":"ٱلْأَرْضِ","c1":"ﮅ","c2":"ﱴ","l":6,"ct":"word"},{"id":24610,"s":47,"a":22,"p":9,"t":"وَتُقَطِّعُوٓا۟","c1":"ﮆ","c2":"ﱵ","l":6,"ct":"word"},{"id":24611,"s":47,"a":22,"p":10,"t":"أَرْحَامَكُمْ","c1":"ﮇ","c2":"ﱶ","l":6,"ct":"word"},{"id":24612,"s":47,"a":22,"p":11,"t":"٢٢","c1":"ﮈ","c2":"ﱷ","l":6,"ct":"end"},{"id":25685,"s":47,"a":23,"p":1,"t":"أُو۟لَـٰٓئِكَ","c1":"ﮉ","c2":"ﱸ","l":6,"ct":"word"},{"id":25686,"s":47,"a":23,"p":2,"t":"ٱلَّذِينَ","c1":"ﮊ","c2":"ﱹ","l":6,"ct":"word"},{"id":25687,"s":47,"a":23,"p":3,"t":"لَعَنَهُمُ","c1":"ﮋ","c2":"ﱺ","l":6,"ct":"word"},{"id":25688,"s":47,"a":23,"p":4,"t":"ٱللَّهُ","c1":"ﮌ","c2":"ﱻ","l":7,"ct":"word"},{"id":25689,"s":47,"a":23,"p":5,"t":"فَأَصَمَّهُمْ","c1":"ﮍ","c2":"ﱼ","l":7,"ct":"word"},{"id":25690,"s":47,"a":23,"p":6,"t":"وَأَعْمَىٰٓ","c1":"ﮎ","c2":"ﱽ","l":7,"ct":"word"},{"id":25691,"s":47,"a":23,"p":7,"t":"أَبْصَـٰرَهُمْ","c1":"ﮏ","c2":"ﱾ","l":7,"ct":"word"},{"id":25692,"s":47,"a":23,"p":8,"t":"٢٣","c1":"ﮐ","c2":"ﱿ","l":7,"ct":"end"},{"id":26638,"s":47,"a":24,"p":1,"t":"أَفَلَا","c1":"ﮑ","c2":"ﲀ","l":7,"ct":"word"},{"id":26639,"s":47,"a":24,"p":2,"t":"يَتَدَبَّرُونَ","c1":"ﮒ","c2":"ﲁ","l":7,"ct":"word"},{"id":26640,"s":47,"a":24,"p":3,"t":"ٱلْقُرْءَانَ","c1":"ﮓ","c2":"ﲂ","l":7,"ct":"word"},{"id":26641,"s":47,"a":24,"p":4,"t":"أَمْ","c1":"ﮔ","c2":"ﲃ","l":8,"ct":"word"},{"id":26642,"s":47,"a":24,"p":5,"t":"عَلَىٰ","c1":"ﮕ","c2":"ﲄ","l":8,"ct":"word"},{"id":26643,"s":47,"a":24,"p":6,"t":"قُلُوبٍ","c1":"ﮖ","c2":"ﲅ","l":8,"ct":"word"},{"id":26644,"s":47,"a":24,"p":7,"t":"أَقْفَالُهَآ","c1":"ﮗ","c2":"ﲆ","l":8,"ct":"word"},{"id":26645,"s":47,"a":24,"p":8,"t":"٢٤","c1":"ﮘ","c2":"ﲇ","l":8,"ct":"end"},{"id":27772,"s":47,"a":25,"p":1,"t":"إِنَّ","c1":"ﮙ","c2":"ﲈ","l":8,"ct":"word"},{"id":27773,"s":47,"a":25,"p":2,"t":"ٱلَّذِينَ","c1":"ﮚ","c2":"ﲉ","l":8,"ct":"word"},{"id":27774,"s":47,"a":25,"p":3,"t":"ٱرْتَدُّوا۟","c1":"ﮛ","c2":"ﲊ","l":8,"ct":"word"},{"id":27775,"s":47,"a":25,"p":4,"t":"عَلَىٰٓ","c1":"ﮜ","c2":"ﲋ","l":8,"ct":"word"},{"id":27776,"s":47,"a":25,"p":5,"t":"أَدْبَـٰرِهِم","c1":"ﮝ","c2":"ﲌ","l":8,"ct":"word"},{"id":27777,"s":47,"a":25,"p":6,"t":"مِّنۢ","c1":"ﮞ","c2":"ﲍ","l":9,"ct":"word"},{"id":27778,"s":47,"a":25,"p":7,"t":"بَعْدِ","c1":"ﮟ","c2":"ﲎ","l":9,"ct":"word"},{"id":27779,"s":47,"a":25,"p":8,"t":"مَا","c1":"ﮠ","c2":"ﲏ","l":9,"ct":"word"},{"id":27780,"s":47,"a":25,"p":9,"t":"تَبَيَّنَ","c1":"ﮡ","c2":"ﲐ","l":9,"ct":"word"},{"id":27781,"s":47,"a":25,"p":10,"t":"لَهُمُ","c1":"ﮢ","c2":"ﲑ","l":9,"ct":"word"},{"id":27782,"s":47,"a":25,"p":11,"t":"ٱلْهُدَى ۙ","c1":"ﮣﮤ","c2":"ﲒ","l":9,"ct":"word"},{"id":27784,"s":47,"a":25,"p":12,"t":"ٱلشَّيْطَـٰنُ","c1":"ﮥ","c2":"ﲓ","l":9,"ct":"word"},{"id":27785,"s":47,"a":25,"p":13,"t":"سَوَّلَ","c1":"ﮦ","c2":"ﲔ","l":9,"ct":"word"},{"id":27786,"s":47,"a":25,"p":14,"t":"لَهُمْ","c1":"ﮧ","c2":"ﲕ","l":9,"ct":"word"},{"id":27787,"s":47,"a":25,"p":15,"t":"وَأَمْلَىٰ","c1":"ﮨ","c2":"ﲖ","l":9,"ct":"word"},{"id":27788,"s":47,"a":25,"p":16,"t":"لَهُمْ","c1":"ﮩ","c2":"ﲗ","l":10,"ct":"word"},{"id":27789,"s":47,"a":25,"p":17,"t":"٢٥","c1":"ﮪ","c2":"ﲘ","l":10,"ct":"end"},{"id":28725,"s":47,"a":26,"p":1,"t":"ذَٰلِكَ","c1":"ﮫ","c2":"ﲙ","l":10,"ct":"word"},{"id":28726,"s":47,"a":26,"p":2,"t":"بِأَنَّهُمْ","c1":"ﮬ","c2":"ﲚ","l":10,"ct":"word"},{"id":28727,"s":47,"a":26,"p":3,"t":"قَالُوا۟","c1":"ﮭ","c2":"ﲛ","l":10,"ct":"word"},{"id":28728,"s":47,"a":26,"p":4,"t":"لِلَّذِينَ","c1":"ﮮ","c2":"ﲜ","l":10,"ct":"word"},{"id":28729,"s":47,"a":26,"p":5,"t":"كَرِهُوا۟","c1":"ﮯ","c2":"ﲝ","l":10,"ct":"word"},{"id":28730,"s":47,"a":26,"p":6,"t":"مَا","c1":"ﮰ","c2":"ﲞ","l":10,"ct":"word"},{"id":28731,"s":47,"a":26,"p":7,"t":"نَزَّلَ","c1":"ﮱ","c2":"ﲟ","l":10,"ct":"word"},{"id":28732,"s":47,"a":26,"p":8,"t":"ٱللَّهُ","c1":"ﯓ","c2":"ﲠ","l":10,"ct":"word"},{"id":28733,"s":47,"a":26,"p":9,"t":"سَنُطِيعُكُمْ","c1":"ﯔ","c2":"ﲡ","l":11,"ct":"word"},{"id":28734,"s":47,"a":26,"p":10,"t":"فِى","c1":"ﯕ","c2":"ﲢ","l":11,"ct":"word"},{"id":28735,"s":47,"a":26,"p":11,"t":"بَعْضِ","c1":"ﯖ","c2":"ﲣ","l":11,"ct":"word"},{"id":28736,"s":47,"a":26,"p":12,"t":"ٱلْأَمْرِ ۖ","c1":"ﯗﯘ","c2":"ﲤﲥ","l":11,"ct":"word"},{"id":28738,"s":47,"a":26,"p":13,"t":"وَٱللَّهُ","c1":"ﯙ","c2":"ﲦ","l":11,"ct":"word"},{"id":28739,"s":47,"a":26,"p":14,"t":"يَعْلَمُ","c1":"ﯚ","c2":"ﲧ","l":11,"ct":"word"},{"id":28740,"s":47,"a":26,"p":15,"t":"إِسْرَارَهُمْ","c1":"ﯛ","c2":"ﲨ","l":11,"ct":"word"},{"id":28741,"s":47,"a":26,"p":16,"t":"٢٦","c1":"ﯜ","c2":"ﲩ","l":11,"ct":"end"},{"id":29610,"s":47,"a":27,"p":1,"t":"فَكَيْفَ","c1":"ﯝ","c2":"ﲪ","l":12,"ct":"word"},{"id":29611,"s":47,"a":27,"p":2,"t":"إِذَا","c1":"ﯞ","c2":"ﲫ","l":12,"ct":"word"},{"id":29612,"s":47,"a":27,"p":3,"t":"تَوَفَّتْهُمُ","c1":"ﯟ","c2":"ﲬ","l":12,"ct":"word"},{"id":29613,"s":47,"a":27,"p":4,"t":"ٱلْمَلَـٰٓئِكَةُ","c1":"ﯠ","c2":"ﲭ","l":12,"ct":"word"},{"id":29614,"s":47,"a":27,"p":5,"t":"يَضْرِبُونَ","c1":"ﯡ","c2":"ﲮ","l":12,"ct":"word"},{"id":29615,"s":47,"a":27,"p":6,"t":"وُجُوهَهُمْ","c1":"ﯢ","c2":"ﲯ","l":12,"ct":"word"},{"id":29616,"s":47,"a":27,"p":7,"t":"وَأَدْبَـٰرَهُمْ","c1":"ﯣ","c2":"ﲰ","l":13,"ct":"word"},{"id":29617,"s":47,"a":27,"p":8,"t":"٢٧","c1":"ﯤ","c2":"ﲱ","l":13,"ct":"end"},{"id":30653,"s":47,"a":28,"p":1,"t":"ذَٰلِكَ","c1":"ﯥ","c2":"ﲲ","l":13,"ct":"word"},{"id":30654,"s":47,"a":28,"p":2,"t":"بِأَنَّهُمُ","c1":"ﯦ","c2":"ﲳ","l":13,"ct":"word"},{"id":30655,"s":47,"a":28,"p":3,"t":"ٱتَّبَعُوا۟","c1":"ﯧ","c2":"ﲴ","l":13,"ct":"word"},{"id":30656,"s":47,"a":28,"p":4,"t":"مَآ","c1":"ﯨ","c2":"ﲵ","l":13,"ct":"word"},{"id":30657,"s":47,"a":28,"p":5,"t":"أَسْخَطَ","c1":"ﯩ","c2":"ﲶ","l":13,"ct":"word"},{"id":30658,"s":47,"a":28,"p":6,"t":"ٱللَّهَ","c1":"ﯪ","c2":"ﲷ","l":13,"ct":"word"},{"id":30659,"s":47,"a":28,"p":7,"t":"وَكَرِهُوا۟","c1":"ﯫ","c2":"ﲸ","l":14,"ct":"word"},{"id":30660,"s":47,"a":28,"p":8,"t":"رِضْوَٰنَهُۥ","c1":"ﯬ","c2":"ﲹ","l":14,"ct":"word"},{"id":30661,"s":47,"a":28,"p":9,"t":"فَأَحْبَطَ","c1":"ﯭ","c2":"ﲺ","l":14,"ct":"word"},{"id":30662,"s":47,"a":28,"p":10,"t":"أَعْمَـٰلَهُمْ","c1":"ﯮ","c2":"ﲻ","l":14,"ct":"word"},{"id":30663,"s":47,"a":28,"p":11,"t":"٢٨","c1":"ﯯ","c2":"ﲼ","l":14,"ct":"end"},{"id":32374,"s":47,"a":29,"p":1,"t":"أَمْ","c1":"ﯰ","c2":"ﲽ","l":14,"ct":"word"},{"id":32375,"s":47,"a":29,"p":2,"t":"حَسِبَ","c1":"ﯱ","c2":"ﲾ","l":14,"ct":"word"},{"id":32376,"s":47,"a":29,"p":3,"t":"ٱلَّذِينَ","c1":"ﯲ","c2":"ﲿ","l":15,"ct":"word"},{"id":32377,"s":47,"a":29,"p":4,"t":"فِى","c1":"ﯳ","c2":"ﳀ","l":15,"ct":"word"},{"id":32378,"s":47,"a":29,"p":5,"t":"قُلُوبِهِم","c1":"ﯴ","c2":"ﳁ","l":15,"ct":"word"},{"id":32379,"s":47,"a":29,"p":6,"t":"مَّرَضٌ","c1":"ﯵ","c2":"ﳂ","l":15,"ct":"word"},{"id":32380,"s":47,"a":29,"p":7,"t":"أَن","c1":"ﯶ","c2":"ﳃ","l":15,"ct":"word"},{"id":32381,"s":47,"a":29,"p":8,"t":"لَّن","c1":"ﯷ","c2":"ﳄ","l":15,"ct":"word"},{"id":32382,"s":47,"a":29,"p":9,"t":"يُخْرِجَ","c1":"ﯸ","c2":"ﳅ","l":15,"ct":"word"},{"id":32383,"s":47,"a":29,"p":10,"t":"ٱللَّهُ","c1":"ﯹ","c2":"ﳆ","l":15,"ct":"word"},{"id":32384,"s":47,"a":29,"p":11,"t":"أَضْغَـٰنَهُمْ","c1":"ﯺ","c2":"ﳇ","l":15,"ct":"word"},{"id":32385,"s":47,"a":29,"p":12,"t":"٢٩","c1":"ﯻ","c2":"ﳈ","l":15,"ct":"end"}]